{
  "function": "DoControllerActions",
  "nodes": [
    {
      "id": 0,
      "label": "entry:DoControllerActions",
      "line": 46
    },
    {
      "id": 1,
      "label": "if (...)",
      "line": 54
    },
    {
      "id": 2,
      "label": "merge",
      "line": 58
    },
    {
      "id": 3,
      "label": "then",
      "line": 54
    },
    {
      "id": 4,
      "label": "if (...)",
      "line": 70
    },
    {
      "id": 5,
      "label": "merge",
      "line": 74
    },
    {
      "id": 6,
      "label": "then",
      "line": 70
    },
    {
      "id": 7,
      "label": "if (...)",
      "line": 82
    },
    {
      "id": 8,
      "label": "merge",
      "line": 87
    },
    {
      "id": 9,
      "label": "then",
      "line": 82
    },
    {
      "id": 10,
      "label": "if (...)",
      "line": 98
    },
    {
      "id": 11,
      "label": "merge",
      "line": 102
    },
    {
      "id": 12,
      "label": "then",
      "line": 98
    },
    {
      "id": 13,
      "label": "if (...)",
      "line": 108
    },
    {
      "id": 14,
      "label": "merge",
      "line": 114
    },
    {
      "id": 15,
      "label": "then",
      "line": 108
    },
    {
      "id": 16,
      "label": "if (...)",
      "line": 121
    },
    {
      "id": 17,
      "label": "merge",
      "line": 127
    },
    {
      "id": 18,
      "label": "then",
      "line": 121
    },
    {
      "id": 19,
      "label": "if (...)",
      "line": 139
    },
    {
      "id": 20,
      "label": "merge",
      "line": 143
    },
    {
      "id": 21,
      "label": "then",
      "line": 139
    },
    {
      "id": 22,
      "label": "if (...)",
      "line": 149
    },
    {
      "id": 23,
      "label": "merge",
      "line": 155
    },
    {
      "id": 24,
      "label": "then",
      "line": 149
    },
    {
      "id": 25,
      "label": "loop (for_statement)",
      "line": 158
    },
    {
      "id": 26,
      "label": "loop_exit",
      "line": 236
    },
    {
      "id": 27,
      "label": "body",
      "line": 158
    },
    {
      "id": 28,
      "label": "if (...)",
      "line": 248
    },
    {
      "id": 29,
      "label": "merge",
      "line": 252
    },
    {
      "id": 30,
      "label": "then",
      "line": 248
    },
    {
      "id": 31,
      "label": "if (...)",
      "line": 265
    },
    {
      "id": 32,
      "label": "merge",
      "line": 269
    },
    {
      "id": 33,
      "label": "then",
      "line": 265
    },
    {
      "id": 34,
      "label": "if (...)",
      "line": 282
    },
    {
      "id": 35,
      "label": "merge",
      "line": 286
    },
    {
      "id": 36,
      "label": "then",
      "line": 282
    },
    {
      "id": 37,
      "label": "if (...)",
      "line": 288
    },
    {
      "id": 38,
      "label": "merge",
      "line": 292
    },
    {
      "id": 39,
      "label": "then",
      "line": 288
    },
    {
      "id": 40,
      "label": "return_statement",
      "line": 294
    },
    {
      "id": 41,
      "label": "exit:DoControllerActions",
      "line": 295
    }
  ],
  "edges": [
    {
      "from": 0,
      "to": 1
    },
    {
      "from": 1,
      "to": 3,
      "label": "true"
    },
    {
      "from": 3,
      "to": 2
    },
    {
      "from": 1,
      "to": 2,
      "label": "false"
    },
    {
      "from": 2,
      "to": 4
    },
    {
      "from": 4,
      "to": 6,
      "label": "true"
    },
    {
      "from": 6,
      "to": 5
    },
    {
      "from": 4,
      "to": 5,
      "label": "false"
    },
    {
      "from": 5,
      "to": 7
    },
    {
      "from": 7,
      "to": 9,
      "label": "true"
    },
    {
      "from": 9,
      "to": 8
    },
    {
      "from": 7,
      "to": 8,
      "label": "false"
    },
    {
      "from": 8,
      "to": 10
    },
    {
      "from": 10,
      "to": 12,
      "label": "true"
    },
    {
      "from": 12,
      "to": 11
    },
    {
      "from": 10,
      "to": 11,
      "label": "false"
    },
    {
      "from": 11,
      "to": 13
    },
    {
      "from": 13,
      "to": 15,
      "label": "true"
    },
    {
      "from": 15,
      "to": 14
    },
    {
      "from": 13,
      "to": 14,
      "label": "false"
    },
    {
      "from": 14,
      "to": 16
    },
    {
      "from": 16,
      "to": 18,
      "label": "true"
    },
    {
      "from": 18,
      "to": 17
    },
    {
      "from": 16,
      "to": 17,
      "label": "false"
    },
    {
      "from": 17,
      "to": 19
    },
    {
      "from": 19,
      "to": 21,
      "label": "true"
    },
    {
      "from": 21,
      "to": 20
    },
    {
      "from": 19,
      "to": 20,
      "label": "false"
    },
    {
      "from": 20,
      "to": 22
    },
    {
      "from": 22,
      "to": 24,
      "label": "true"
    },
    {
      "from": 24,
      "to": 23
    },
    {
      "from": 22,
      "to": 23,
      "label": "false"
    },
    {
      "from": 23,
      "to": 25
    },
    {
      "from": 25,
      "to": 26,
      "label": "done"
    },
    {
      "from": 25,
      "to": 27,
      "label": "continue"
    },
    {
      "from": 27,
      "to": 25,
      "label": "back"
    },
    {
      "from": 26,
      "to": 28
    },
    {
      "from": 28,
      "to": 30,
      "label": "true"
    },
    {
      "from": 30,
      "to": 29
    },
    {
      "from": 28,
      "to": 29,
      "label": "false"
    },
    {
      "from": 29,
      "to": 31
    },
    {
      "from": 31,
      "to": 33,
      "label": "true"
    },
    {
      "from": 33,
      "to": 32
    },
    {
      "from": 31,
      "to": 32,
      "label": "false"
    },
    {
      "from": 32,
      "to": 34
    },
    {
      "from": 34,
      "to": 36,
      "label": "true"
    },
    {
      "from": 36,
      "to": 35
    },
    {
      "from": 34,
      "to": 35,
      "label": "false"
    },
    {
      "from": 35,
      "to": 37
    },
    {
      "from": 37,
      "to": 39,
      "label": "true"
    },
    {
      "from": 39,
      "to": 38
    },
    {
      "from": 37,
      "to": 38,
      "label": "false"
    },
    {
      "from": 38,
      "to": 40
    },
    {
      "from": 38,
      "to": 41
    }
  ]
}