{
  "function": "ReadyAllSlots",
  "nodes": [
    {
      "id": 0,
      "label": "entry:ReadyAllSlots",
      "line": 140
    },
    {
      "id": 1,
      "label": "loop (for_statement)",
      "line": 142
    },
    {
      "id": 2,
      "label": "loop_exit",
      "line": 145
    },
    {
      "id": 3,
      "label": "body",
      "line": 142
    },
    {
      "id": 4,
      "label": "exit:ReadyAllSlots",
      "line": 146
    }
  ],
  "edges": [
    {
      "from": 0,
      "to": 1
    },
    {
      "from": 1,
      "to": 2,
      "label": "done"
    },
    {
      "from": 1,
      "to": 3,
      "label": "continue"
    },
    {
      "from": 3,
      "to": 1,
      "label": "back"
    },
    {
      "from": 2,
      "to": 4
    }
  ]
}