{
  "function": "check_visitable",
  "nodes": [
    {
      "id": 0,
      "label": "entry:check_visitable",
      "line": 160
    },
    {
      "id": 1,
      "label": "if (...)",
      "line": 163
    },
    {
      "id": 2,
      "label": "merge",
      "line": 166
    },
    {
      "id": 3,
      "label": "then",
      "line": 163
    },
    {
      "id": 4,
      "label": "loop (for_statement)",
      "line": 167
    },
    {
      "id": 5,
      "label": "loop_exit",
      "line": 173
    },
    {
      "id": 6,
      "label": "body",
      "line": 167
    },
    {
      "id": 7,
      "label": "return_statement",
      "line": 174
    },
    {
      "id": 8,
      "label": "exit:check_visitable",
      "line": 175
    }
  ],
  "edges": [
    {
      "from": 0,
      "to": 1
    },
    {
      "from": 1,
      "to": 3,
      "label": "true"
    },
    {
      "from": 3,
      "to": 2
    },
    {
      "from": 1,
      "to": 2,
      "label": "false"
    },
    {
      "from": 2,
      "to": 4
    },
    {
      "from": 4,
      "to": 5,
      "label": "done"
    },
    {
      "from": 4,
      "to": 6,
      "label": "continue"
    },
    {
      "from": 6,
      "to": 4,
      "label": "back"
    },
    {
      "from": 5,
      "to": 7
    },
    {
      "from": 5,
      "to": 8
    }
  ]
}