{
  "function": "IsWriteableForOwner",
  "nodes": [
    {
      "id": 0,
      "label": "entry:IsWriteableForOwner",
      "line": 71
    },
    {
      "id": 1,
      "label": "if (...)",
      "line": 77
    },
    {
      "id": 2,
      "label": "merge",
      "line": 80
    },
    {
      "id": 3,
      "label": "then",
      "line": 77
    },
    {
      "id": 4,
      "label": "exit:IsWriteableForOwner",
      "line": 84
    }
  ],
  "edges": [
    {
      "from": 0,
      "to": 1
    },
    {
      "from": 1,
      "to": 3,
      "label": "true"
    },
    {
      "from": 3,
      "to": 2
    },
    {
      "from": 1,
      "to": 2,
      "label": "false"
    },
    {
      "from": 2,
      "to": 4
    }
  ]
}