[
  {
    "function": "main",
    "file": "build.rs",
    "start_line": 3,
    "cyclomatic_complexity": 2,
    "nesting_depth": 3,
    "loc": 24,
    "param_count": 0,
    "flags": []
  },
  {
    "function": "main",
    "file": "service_discovery/core/src/main.rs",
    "start_line": 30,
    "cyclomatic_complexity": 1,
    "nesting_depth": 1,
    "loc": 23,
    "param_count": 0,
    "flags": []
  },
  {
    "function": "new",
    "file": "service_discovery/core/src/service_registry_impl.rs",
    "start_line": 30,
    "cyclomatic_complexity": 1,
    "nesting_depth": 1,
    "loc": 5,
    "param_count": 1,
    "flags": []
  },
  {
    "function": "register",
    "file": "service_discovery/core/src/service_registry_impl.rs",
    "start_line": 44,
    "cyclomatic_complexity": 4,
    "nesting_depth": 4,
    "loc": 33,
    "param_count": 2,
    "flags": [
      "high_nesting"
    ]
  },
  {
    "function": "unregister",
    "file": "service_discovery/core/src/service_registry_impl.rs",
    "start_line": 83,
    "cyclomatic_complexity": 4,
    "nesting_depth": 3,
    "loc": 28,
    "param_count": 2,
    "flags": []
  },
  {
    "function": "discover_by_namespace",
    "file": "service_discovery/core/src/service_registry_impl.rs",
    "start_line": 117,
    "cyclomatic_complexity": 2,
    "nesting_depth": 3,
    "loc": 18,
    "param_count": 2,
    "flags": []
  },
  {
    "function": "discover",
    "file": "service_discovery/core/src/service_registry_impl.rs",
    "start_line": 142,
    "cyclomatic_complexity": 4,
    "nesting_depth": 3,
    "loc": 36,
    "param_count": 2,
    "flags": []
  },
  {
    "function": "list",
    "file": "service_discovery/core/src/service_registry_impl.rs",
    "start_line": 184,
    "cyclomatic_complexity": 1,
    "nesting_depth": 1,
    "loc": 6,
    "param_count": 2,
    "flags": []
  },
  {
    "function": "has_service",
    "file": "service_discovery/core/src/service_registry_impl.rs",
    "start_line": 207,
    "cyclomatic_complexity": 1,
    "nesting_depth": 2,
    "loc": 10,
    "param_count": 2,
    "flags": []
  },
  {
    "function": "register_test",
    "file": "service_discovery/core/src/service_registry_impl.rs",
    "start_line": 219,
    "cyclomatic_complexity": 1,
    "nesting_depth": 1,
    "loc": 39,
    "param_count": 0,
    "flags": []
  },
  {
    "function": "unregister_test",
    "file": "service_discovery/core/src/service_registry_impl.rs",
    "start_line": 260,
    "cyclomatic_complexity": 1,
    "nesting_depth": 2,
    "loc": 47,
    "param_count": 0,
    "flags": []
  },
  {
    "function": "discover_test",
    "file": "service_discovery/core/src/service_registry_impl.rs",
    "start_line": 309,
    "cyclomatic_complexity": 1,
    "nesting_depth": 2,
    "loc": 57,
    "param_count": 0,
    "flags": []
  },
  {
    "function": "list_test",
    "file": "service_discovery/core/src/service_registry_impl.rs",
    "start_line": 368,
    "cyclomatic_complexity": 1,
    "nesting_depth": 2,
    "loc": 48,
    "param_count": 0,
    "flags": []
  },
  {
    "function": "main",
    "file": "service_discovery/samples/simple-discovery/consumer/src/main.rs",
    "start_line": 31,
    "cyclomatic_complexity": 9,
    "nesting_depth": 5,
    "loc": 42,
    "param_count": 0,
    "flags": [
      "high_nesting"
    ]
  },
  {
    "function": "say_hello",
    "file": "service_discovery/samples/simple-discovery/provider/src/hello_world_impl.rs",
    "start_line": 26,
    "cyclomatic_complexity": 1,
    "nesting_depth": 1,
    "loc": 12,
    "param_count": 2,
    "flags": []
  },
  {
    "function": "main",
    "file": "service_discovery/samples/simple-discovery/provider/src/main.rs",
    "start_line": 39,
    "cyclomatic_complexity": 1,
    "nesting_depth": 1,
    "loc": 40,
    "param_count": 0,
    "flags": []
  },
  {
    "function": "main",
    "file": "service_discovery/samples/proto_build/build.rs",
    "start_line": 5,
    "cyclomatic_complexity": 1,
    "nesting_depth": 1,
    "loc": 4,
    "param_count": 0,
    "flags": []
  },
  {
    "function": "main",
    "file": "service_discovery/proto_build/build.rs",
    "start_line": 5,
    "cyclomatic_complexity": 1,
    "nesting_depth": 1,
    "loc": 4,
    "param_count": 0,
    "flags": []
  },
  {
    "function": "map_err_with",
    "file": "intent_brokering/common/src/error.rs",
    "start_line": 26,
    "cyclomatic_complexity": 1,
    "nesting_depth": 1,
    "loc": 6,
    "param_count": 2,
    "flags": []
  },
  {
    "function": "new",
    "file": "intent_brokering/common/src/error.rs",
    "start_line": 35,
    "cyclomatic_complexity": 1,
    "nesting_depth": 1,
    "loc": 3,
    "param_count": 1,
    "flags": []
  },
  {
    "function": "from_error",
    "file": "intent_brokering/common/src/error.rs",
    "start_line": 39,
    "cyclomatic_complexity": 1,
    "nesting_depth": 1,
    "loc": 6,
    "param_count": 2,
    "flags": []
  },
  {
    "function": "message",
    "file": "intent_brokering/common/src/error.rs",
    "start_line": 46,
    "cyclomatic_complexity": 1,
    "nesting_depth": 1,
    "loc": 3,
    "param_count": 1,
    "flags": []
  },
  {
    "function": "fmt",
    "file": "intent_brokering/common/src/error.rs",
    "start_line": 52,
    "cyclomatic_complexity": 1,
    "nesting_depth": 1,
    "loc": 3,
    "param_count": 2,
    "flags": []
  },
  {
    "function": "source",
    "file": "intent_brokering/common/src/error.rs",
    "start_line": 58,
    "cyclomatic_complexity": 1,
    "nesting_depth": 1,
    "loc": 3,
    "param_count": 1,
    "flags": []
  },
  {
    "function": "from",
    "file": "intent_brokering/common/src/error.rs",
    "start_line": 64,
    "cyclomatic_complexity": 1,
    "nesting_depth": 1,
    "loc": 3,
    "param_count": 1,
    "flags": []
  },
  {
    "function": "can_display_error",
    "file": "intent_brokering/common/src/error.rs",
    "start_line": 74,
    "cyclomatic_complexity": 1,
    "nesting_depth": 1,
    "loc": 3,
    "param_count": 0,
    "flags": []
  },
  {
    "function": "can_debug_error",
    "file": "intent_brokering/common/src/error.rs",
    "start_line": 79,
    "cyclomatic_complexity": 1,
    "nesting_depth": 1,
    "loc": 6,
    "param_count": 0,
    "flags": []
  },
  {
    "function": "can_debug_error_with_source",
    "file": "intent_brokering/common/src/error.rs",
    "start_line": 87,
    "cyclomatic_complexity": 1,
    "nesting_depth": 1,
    "loc": 14,
    "param_count": 0,
    "flags": []
  },
  {
    "function": "can_display_error_with_source",
    "file": "intent_brokering/common/src/error.rs",
    "start_line": 103,
    "cyclomatic_complexity": 1,
    "nesting_depth": 1,
    "loc": 15,
    "param_count": 0,
    "flags": []
  },
  {
    "function": "can_get_source",
    "file": "intent_brokering/common/src/error.rs",
    "start_line": 120,
    "cyclomatic_complexity": 1,
    "nesting_depth": 1,
    "loc": 10,
    "param_count": 0,
    "flags": []
  },
  {
    "function": "map_expect",
    "file": "intent_brokering/common/src/error.rs",
    "start_line": 132,
    "cyclomatic_complexity": 1,
    "nesting_depth": 1,
    "loc": 15,
    "param_count": 0,
    "flags": []
  },
  {
    "function": "get_io_error",
    "file": "intent_brokering/common/src/error.rs",
    "start_line": 148,
    "cyclomatic_complexity": 1,
    "nesting_depth": 1,
    "loc": 3,
    "param_count": 0,
    "flags": []
  },
  {
    "function": "ok",
    "file": "intent_brokering/common/src/ext.rs",
    "start_line": 11,
    "cyclomatic_complexity": 1,
    "nesting_depth": 1,
    "loc": 5,
    "param_count": 1,
    "flags": []
  },
  {
    "function": "ok_with_none_returns_ok_of_some",
    "file": "intent_brokering/common/src/ext.rs",
    "start_line": 26,
    "cyclomatic_complexity": 1,
    "nesting_depth": 1,
    "loc": 6,
    "param_count": 0,
    "flags": []
  },
  {
    "function": "ok_with_some_ok_returns_ok_of_some",
    "file": "intent_brokering/common/src/ext.rs",
    "start_line": 34,
    "cyclomatic_complexity": 1,
    "nesting_depth": 1,
    "loc": 6,
    "param_count": 0,
    "flags": []
  },
  {
    "function": "ok_with_some_err_returns_err_of_some",
    "file": "intent_brokering/common/src/ext.rs",
    "start_line": 42,
    "cyclomatic_complexity": 1,
    "nesting_depth": 1,
    "loc": 6,
    "param_count": 0,
    "flags": []
  },
  {
    "function": "ctrl_c_cancellation",
    "file": "intent_brokering/common/src/shutdown.rs",
    "start_line": 13,
    "cyclomatic_complexity": 2,
    "nesting_depth": 4,
    "loc": 14,
    "param_count": 0,
    "flags": [
      "high_nesting"
    ]
  },
  {
    "function": "serve_with_cancellation",
    "file": "intent_brokering/common/src/shutdown.rs",
    "start_line": 41,
    "cyclomatic_complexity": 1,
    "nesting_depth": 1,
    "loc": 9,
    "param_count": 3,
    "flags": []
  },
  {
    "function": "serve_with_ctrl_c_shutdown",
    "file": "intent_brokering/common/src/shutdown.rs",
    "start_line": 51,
    "cyclomatic_complexity": 1,
    "nesting_depth": 1,
    "loc": 3,
    "param_count": 2,
    "flags": []
  },
  {
    "function": "new",
    "file": "intent_brokering/common/src/streaming_ess.rs",
    "start_line": 28,
    "cyclomatic_complexity": 1,
    "nesting_depth": 1,
    "loc": 3,
    "param_count": 0,
    "flags": []
  },
  {
    "function": "default",
    "file": "intent_brokering/common/src/streaming_ess.rs",
    "start_line": 34,
    "cyclomatic_complexity": 1,
    "nesting_depth": 1,
    "loc": 3,
    "param_count": 0,
    "flags": []
  },
  {
    "function": "serve_subscriptions",
    "file": "intent_brokering/common/src/streaming_ess.rs",
    "start_line": 40,
    "cyclomatic_complexity": 1,
    "nesting_depth": 3,
    "loc": 27,
    "param_count": 3,
    "flags": []
  },
  {
    "function": "<anonymous>",
    "file": "intent_brokering/common/src/streaming_ess.rs",
    "start_line": 43,
    "cyclomatic_complexity": 1,
    "nesting_depth": 0,
    "loc": 1,
    "param_count": 1,
    "flags": []
  },
  {
    "function": "open",
    "file": "intent_brokering/common/src/streaming_ess.rs",
    "start_line": 76,
    "cyclomatic_complexity": 1,
    "nesting_depth": 1,
    "loc": 12,
    "param_count": 2,
    "flags": []
  },
  {
    "function": "deref",
    "file": "intent_brokering/common/src/streaming_ess.rs",
    "start_line": 93,
    "cyclomatic_complexity": 1,
    "nesting_depth": 1,
    "loc": 3,
    "param_count": 1,
    "flags": []
  },
  {
    "function": "open_should_set_channel_id",
    "file": "intent_brokering/common/src/streaming_ess.rs",
    "start_line": 112,
    "cyclomatic_complexity": 1,
    "nesting_depth": 1,
    "loc": 10,
    "param_count": 0,
    "flags": []
  },
  {
    "function": "serve_subscriptions_should_serve_subscription_for_event",
    "file": "intent_brokering/common/src/streaming_ess.rs",
    "start_line": 124,
    "cyclomatic_complexity": 1,
    "nesting_depth": 2,
    "loc": 40,
    "param_count": 0,
    "flags": []
  },
  {
    "function": "serve_subscriptions_should_error_when_no_client_active",
    "file": "intent_brokering/common/src/streaming_ess.rs",
    "start_line": 166,
    "cyclomatic_complexity": 1,
    "nesting_depth": 1,
    "loc": 15,
    "param_count": 0,
    "flags": []
  },
  {
    "function": "setup",
    "file": "intent_brokering/common/src/streaming_ess.rs",
    "start_line": 182,
    "cyclomatic_complexity": 1,
    "nesting_depth": 1,
    "loc": 3,
    "param_count": 0,
    "flags": []
  },
  {
    "function": "handle",
    "file": "intent_brokering/common/src/tokio_runtime_fork.rs",
    "start_line": 14,
    "cyclomatic_complexity": 1,
    "nesting_depth": 1,
    "loc": 3,
    "param_count": 1,
    "flags": []
  },
  {
    "function": "drop",
    "file": "intent_brokering/common/src/tokio_runtime_fork.rs",
    "start_line": 20,
    "cyclomatic_complexity": 1,
    "nesting_depth": 1,
    "loc": 7,
    "param_count": 1,
    "flags": []
  },
  {
    "function": "fork",
    "file": "intent_brokering/common/src/tokio_runtime_fork.rs",
    "start_line": 34,
    "cyclomatic_complexity": 1,
    "nesting_depth": 3,
    "loc": 12,
    "param_count": 1,
    "flags": []
  },
  {
    "function": "regex_pattern_from_query",
    "file": "intent_brokering/common/src/query.rs",
    "start_line": 7,
    "cyclomatic_complexity": 1,
    "nesting_depth": 1,
    "loc": 3,
    "param_count": 1,
    "flags": []
  },
  {
    "function": "regex_from_query",
    "file": "intent_brokering/common/src/query.rs",
    "start_line": 11,
    "cyclomatic_complexity": 1,
    "nesting_depth": 1,
    "loc": 3,
    "param_count": 1,
    "flags": []
  },
  {
    "function": "test_regex_query_conversion",
    "file": "intent_brokering/common/src/query.rs",
    "start_line": 20,
    "cyclomatic_complexity": 1,
    "nesting_depth": 2,
    "loc": 23,
    "param_count": 0,
    "flags": []
  },
  {
    "function": "test",
    "file": "intent_brokering/common/src/query.rs",
    "start_line": 33,
    "cyclomatic_complexity": 1,
    "nesting_depth": 1,
    "loc": 9,
    "param_count": 3,
    "flags": []
  },
  {
    "function": "env",
    "file": "intent_brokering/common/src/config.rs",
    "start_line": 9,
    "cyclomatic_complexity": 1,
    "nesting_depth": 1,
    "loc": 12,
    "param_count": 1,
    "flags": []
  },
  {
    "function": "try_env",
    "file": "intent_brokering/common/src/config.rs",
    "start_line": 23,
    "cyclomatic_complexity": 1,
    "nesting_depth": 1,
    "loc": 11,
    "param_count": 1,
    "flags": []
  },
  {
    "function": "var_os",
    "file": "intent_brokering/common/src/config.rs",
    "start_line": 46,
    "cyclomatic_complexity": 5,
    "nesting_depth": 2,
    "loc": 7,
    "param_count": 1,
    "flags": []
  },
  {
    "function": "env_variable_is_found",
    "file": "intent_brokering/common/src/config.rs",
    "start_line": 55,
    "cyclomatic_complexity": 1,
    "nesting_depth": 1,
    "loc": 4,
    "param_count": 0,
    "flags": []
  },
  {
    "function": "env_variable_not_set",
    "file": "intent_brokering/common/src/config.rs",
    "start_line": 61,
    "cyclomatic_complexity": 1,
    "nesting_depth": 1,
    "loc": 4,
    "param_count": 0,
    "flags": []
  },
  {
    "function": "try_env_variable_is_found",
    "file": "intent_brokering/common/src/config.rs",
    "start_line": 67,
    "cyclomatic_complexity": 1,
    "nesting_depth": 1,
    "loc": 4,
    "param_count": 0,
    "flags": []
  },
  {
    "function": "try_env_variable_not_set",
    "file": "intent_brokering/common/src/config.rs",
    "start_line": 73,
    "cyclomatic_complexity": 1,
    "nesting_depth": 1,
    "loc": 4,
    "param_count": 0,
    "flags": []
  },
  {
    "function": "try_env_variable_is_expected_type",
    "file": "intent_brokering/common/src/config.rs",
    "start_line": 79,
    "cyclomatic_complexity": 1,
    "nesting_depth": 1,
    "loc": 4,
    "param_count": 0,
    "flags": []
  },
  {
    "function": "try_env_variable_is_not_expected_type",
    "file": "intent_brokering/common/src/config.rs",
    "start_line": 85,
    "cyclomatic_complexity": 1,
    "nesting_depth": 2,
    "loc": 8,
    "param_count": 0,
    "flags": []
  },
  {
    "function": "main",
    "file": "intent_brokering/src/main.rs",
    "start_line": 30,
    "cyclomatic_complexity": 4,
    "nesting_depth": 4,
    "loc": 79,
    "param_count": 0,
    "flags": [
      "high_nesting"
    ]
  },
  {
    "function": "registry_prune_loop",
    "file": "intent_brokering/src/main.rs",
    "start_line": 110,
    "cyclomatic_complexity": 2,
    "nesting_depth": 4,
    "loc": 24,
    "param_count": 3,
    "flags": [
      "high_nesting"
    ]
  },
  {
    "function": "new",
    "file": "intent_brokering/src/intent_broker.rs",
    "start_line": 36,
    "cyclomatic_complexity": 1,
    "nesting_depth": 1,
    "loc": 20,
    "param_count": 2,
    "flags": []
  },
  {
    "function": "resolve",
    "file": "intent_brokering/src/intent_broker.rs",
    "start_line": 57,
    "cyclomatic_complexity": 7,
    "nesting_depth": 3,
    "loc": 23,
    "param_count": 2,
    "flags": []
  },
  {
    "function": "binding_into_runtime_binding",
    "file": "intent_brokering/src/intent_broker.rs",
    "start_line": 58,
    "cyclomatic_complexity": 7,
    "nesting_depth": 2,
    "loc": 17,
    "param_count": 2,
    "flags": []
  },
  {
    "function": "refresh",
    "file": "intent_brokering/src/intent_broker.rs",
    "start_line": 81,
    "cyclomatic_complexity": 19,
    "nesting_depth": 7,
    "loc": 54,
    "param_count": 2,
    "flags": [
      "high_complexity",
      "high_nesting"
    ]
  },
  {
    "function": "new",
    "file": "intent_brokering/src/intent_broker.rs",
    "start_line": 143,
    "cyclomatic_complexity": 1,
    "nesting_depth": 1,
    "loc": 3,
    "param_count": 2,
    "flags": []
  },
  {
    "function": "resolve",
    "file": "intent_brokering/src/intent_broker.rs",
    "start_line": 147,
    "cyclomatic_complexity": 1,
    "nesting_depth": 1,
    "loc": 3,
    "param_count": 2,
    "flags": []
  },
  {
    "function": "on_change",
    "file": "intent_brokering/src/intent_broker.rs",
    "start_line": 153,
    "cyclomatic_complexity": 1,
    "nesting_depth": 1,
    "loc": 3,
    "param_count": 2,
    "flags": []
  },
  {
    "function": "when_empty_does_not_resolve",
    "file": "intent_brokering/src/intent_broker.rs",
    "start_line": 179,
    "cyclomatic_complexity": 1,
    "nesting_depth": 1,
    "loc": 8,
    "param_count": 0,
    "flags": []
  },
  {
    "function": "when_broker_contains_different_intent_does_not_resolve",
    "file": "intent_brokering/src/intent_broker.rs",
    "start_line": 189,
    "cyclomatic_complexity": 1,
    "nesting_depth": 1,
    "loc": 7,
    "param_count": 0,
    "flags": []
  },
  {
    "function": "when_modifying_with_empty_services_does_no_longer_resolve_intent",
    "file": "intent_brokering/src/intent_broker.rs",
    "start_line": 198,
    "cyclomatic_complexity": 1,
    "nesting_depth": 1,
    "loc": 11,
    "param_count": 0,
    "flags": []
  },
  {
    "function": "when_removing_does_no_longer_resolve_intent",
    "file": "intent_brokering/src/intent_broker.rs",
    "start_line": 211,
    "cyclomatic_complexity": 1,
    "nesting_depth": 1,
    "loc": 11,
    "param_count": 0,
    "flags": []
  },
  {
    "function": "when_resolve_if_services_are_cloud_and_local_returns_fallback",
    "file": "intent_brokering/src/intent_broker.rs",
    "start_line": 224,
    "cyclomatic_complexity": 1,
    "nesting_depth": 2,
    "loc": 20,
    "param_count": 0,
    "flags": []
  },
  {
    "function": "when_resolve_binding_if_multi_cloud_and_multi_local_returns_cloud_and_local_fallback",
    "file": "intent_brokering/src/intent_broker.rs",
    "start_line": 246,
    "cyclomatic_complexity": 1,
    "nesting_depth": 1,
    "loc": 29,
    "param_count": 0,
    "flags": []
  },
  {
    "function": "when_resolve_with_single_locality_is_remote",
    "file": "intent_brokering/src/intent_broker.rs",
    "start_line": 277,
    "cyclomatic_complexity": 1,
    "nesting_depth": 3,
    "loc": 24,
    "param_count": 0,
    "flags": []
  },
  {
    "function": "test",
    "file": "intent_brokering/src/intent_broker.rs",
    "start_line": 283,
    "cyclomatic_complexity": 1,
    "nesting_depth": 2,
    "loc": 17,
    "param_count": 1,
    "flags": []
  },
  {
    "function": "resolve_system_registry_succeeds",
    "file": "intent_brokering/src/intent_broker.rs",
    "start_line": 303,
    "cyclomatic_complexity": 3,
    "nesting_depth": 3,
    "loc": 17,
    "param_count": 0,
    "flags": []
  },
  {
    "function": "resolve_succeeds_for_system_discover",
    "file": "intent_brokering/src/intent_broker.rs",
    "start_line": 322,
    "cyclomatic_complexity": 3,
    "nesting_depth": 3,
    "loc": 14,
    "param_count": 0,
    "flags": []
  },
  {
    "function": "resolve_succeeds_for_system_subscribe",
    "file": "intent_brokering/src/intent_broker.rs",
    "start_line": 338,
    "cyclomatic_complexity": 3,
    "nesting_depth": 3,
    "loc": 14,
    "param_count": 0,
    "flags": []
  },
  {
    "function": "when_refreshing_does_not_depend_on_previous_state",
    "file": "intent_brokering/src/intent_broker.rs",
    "start_line": 354,
    "cyclomatic_complexity": 1,
    "nesting_depth": 1,
    "loc": 14,
    "param_count": 0,
    "flags": []
  },
  {
    "function": "assert_grpc_binding",
    "file": "intent_brokering/src/intent_broker.rs",
    "start_line": 369,
    "cyclomatic_complexity": 3,
    "nesting_depth": 3,
    "loc": 10,
    "param_count": 2,
    "flags": []
  },
  {
    "function": "<anonymous>",
    "file": "intent_brokering/src/intent_broker.rs",
    "start_line": 371,
    "cyclomatic_complexity": 1,
    "nesting_depth": 0,
    "loc": 1,
    "param_count": 1,
    "flags": []
  },
  {
    "function": "assert_remote_fallback_binding",
    "file": "intent_brokering/src/intent_broker.rs",
    "start_line": 380,
    "cyclomatic_complexity": 6,
    "nesting_depth": 5,
    "loc": 24,
    "param_count": 3,
    "flags": [
      "high_nesting"
    ]
  },
  {
    "function": "<anonymous>",
    "file": "intent_brokering/src/intent_broker.rs",
    "start_line": 382,
    "cyclomatic_complexity": 1,
    "nesting_depth": 0,
    "loc": 1,
    "param_count": 1,
    "flags": []
  },
  {
    "function": "<anonymous>",
    "file": "intent_brokering/src/intent_broker.rs",
    "start_line": 383,
    "cyclomatic_complexity": 1,
    "nesting_depth": 0,
    "loc": 1,
    "param_count": 1,
    "flags": []
  },
  {
    "function": "new",
    "file": "intent_brokering/src/intent_broker.rs",
    "start_line": 414,
    "cyclomatic_complexity": 1,
    "nesting_depth": 1,
    "loc": 5,
    "param_count": 0,
    "flags": []
  },
  {
    "function": "build",
    "file": "intent_brokering/src/intent_broker.rs",
    "start_line": 420,
    "cyclomatic_complexity": 1,
    "nesting_depth": 1,
    "loc": 10,
    "param_count": 1,
    "flags": []
  },
  {
    "function": "execution_locality",
    "file": "intent_brokering/src/intent_broker.rs",
    "start_line": 431,
    "cyclomatic_complexity": 1,
    "nesting_depth": 1,
    "loc": 4,
    "param_count": 2,
    "flags": []
  },
  {
    "function": "service_name",
    "file": "intent_brokering/src/intent_broker.rs",
    "start_line": 436,
    "cyclomatic_complexity": 1,
    "nesting_depth": 1,
    "loc": 4,
    "param_count": 2,
    "flags": []
  },
  {
    "function": "combine",
    "file": "intent_brokering/src/intent_broker.rs",
    "start_line": 441,
    "cyclomatic_complexity": 1,
    "nesting_depth": 2,
    "loc": 21,
    "param_count": 1,
    "flags": []
  },
  {
    "function": "group",
    "file": "intent_brokering/src/execution.rs",
    "start_line": 34,
    "cyclomatic_complexity": 1,
    "nesting_depth": 2,
    "loc": 7,
    "param_count": 1,
    "flags": []
  },
  {
    "function": "execute",
    "file": "intent_brokering/src/execution.rs",
    "start_line": 60,
    "cyclomatic_complexity": 15,
    "nesting_depth": 5,
    "loc": 84,
    "param_count": 2,
    "flags": [
      "high_complexity",
      "high_nesting"
    ]
  },
  {
    "function": "fulfill_response",
    "file": "intent_brokering/src/execution.rs",
    "start_line": 61,
    "cyclomatic_complexity": 1,
    "nesting_depth": 1,
    "loc": 5,
    "param_count": 1,
    "flags": []
  },
  {
    "function": "new",
    "file": "intent_brokering/src/execution.rs",
    "start_line": 178,
    "cyclomatic_complexity": 1,
    "nesting_depth": 1,
    "loc": 3,
    "param_count": 2,
    "flags": []
  },
  {
    "function": "from_result",
    "file": "intent_brokering/src/execution.rs",
    "start_line": 182,
    "cyclomatic_complexity": 1,
    "nesting_depth": 1,
    "loc": 3,
    "param_count": 1,
    "flags": []
  },
  {
    "function": "execute",
    "file": "intent_brokering/src/execution.rs",
    "start_line": 186,
    "cyclomatic_complexity": 2,
    "nesting_depth": 3,
    "loc": 15,
    "param_count": 2,
    "flags": []
  },
  {
    "function": "parse_result",
    "file": "intent_brokering/src/execution.rs",
    "start_line": 202,
    "cyclomatic_complexity": 5,
    "nesting_depth": 2,
    "loc": 12,
    "param_count": 1,
    "flags": []
  },
  {
    "function": "execute_with_empty_intent",
    "file": "intent_brokering/src/execution.rs",
    "start_line": 216,
    "cyclomatic_complexity": 1,
    "nesting_depth": 1,
    "loc": 5,
    "param_count": 1,
    "flags": []
  },
  {
    "function": "fallback_binding_when_first_succeeds_should_return_response",
    "file": "intent_brokering/src/execution.rs",
    "start_line": 223,
    "cyclomatic_complexity": 1,
    "nesting_depth": 1,
    "loc": 12,
    "param_count": 0,
    "flags": []
  },
  {
    "function": "fallback_binding_when_first_fails_returns_second_response",
    "file": "intent_brokering/src/execution.rs",
    "start_line": 237,
    "cyclomatic_complexity": 1,
    "nesting_depth": 1,
    "loc": 13,
    "param_count": 0,
    "flags": []
  },
  {
    "function": "fallback_binding_when_both_fail_returns_second_error",
    "file": "intent_brokering/src/execution.rs",
    "start_line": 252,
    "cyclomatic_complexity": 1,
    "nesting_depth": 1,
    "loc": 12,
    "param_count": 0,
    "flags": []
  },
  {
    "function": "system_inspect_binding_fails_with_non_supported_intent",
    "file": "intent_brokering/src/execution.rs",
    "start_line": 267,
    "cyclomatic_complexity": 1,
    "nesting_depth": 1,
    "loc": 3,
    "param_count": 0,
    "flags": []
  },
  {
    "function": "system_inspect_binding_succeeds",
    "file": "intent_brokering/src/execution.rs",
    "start_line": 272,
    "cyclomatic_complexity": 14,
    "nesting_depth": 4,
    "loc": 75,
    "param_count": 0,
    "flags": [
      "high_complexity",
      "high_nesting"
    ]
  },
  {
    "function": "test",
    "file": "intent_brokering/src/execution.rs",
    "start_line": 282,
    "cyclomatic_complexity": 14,
    "nesting_depth": 3,
    "loc": 64,
    "param_count": 2,
    "flags": [
      "high_complexity"
    ]
  },
  {
    "function": "system_discover_binding_succeeds",
    "file": "intent_brokering/src/execution.rs",
    "start_line": 349,
    "cyclomatic_complexity": 1,
    "nesting_depth": 1,
    "loc": 27,
    "param_count": 0,
    "flags": []
  },
  {
    "function": "system_subscribe_binding_fails_with_non_supported_intent",
    "file": "intent_brokering/src/execution.rs",
    "start_line": 379,
    "cyclomatic_complexity": 1,
    "nesting_depth": 1,
    "loc": 3,
    "param_count": 0,
    "flags": []
  },
  {
    "function": "system_subscribe_binding_succeeds",
    "file": "intent_brokering/src/execution.rs",
    "start_line": 384,
    "cyclomatic_complexity": 1,
    "nesting_depth": 1,
    "loc": 37,
    "param_count": 0,
    "flags": []
  },
  {
    "function": "execute_system_inspect",
    "file": "intent_brokering/src/execution.rs",
    "start_line": 422,
    "cyclomatic_complexity": 4,
    "nesting_depth": 2,
    "loc": 12,
    "param_count": 2,
    "flags": []
  },
  {
    "function": "collect_when_stable",
    "file": "intent_brokering/src/execution.rs",
    "start_line": 449,
    "cyclomatic_complexity": 1,
    "nesting_depth": 1,
    "loc": 9,
    "param_count": 1,
    "flags": []
  },
  {
    "function": "new",
    "file": "intent_brokering/src/intent_brokering_grpc.rs",
    "start_line": 43,
    "cyclomatic_complexity": 1,
    "nesting_depth": 1,
    "loc": 3,
    "param_count": 2,
    "flags": []
  },
  {
    "function": "registry_do",
    "file": "intent_brokering/src/intent_brokering_grpc.rs",
    "start_line": 47,
    "cyclomatic_complexity": 1,
    "nesting_depth": 1,
    "loc": 4,
    "param_count": 2,
    "flags": []
  },
  {
    "function": "<anonymous>",
    "file": "intent_brokering/src/intent_brokering_grpc.rs",
    "start_line": 47,
    "cyclomatic_complexity": 1,
    "nesting_depth": 0,
    "loc": 1,
    "param_count": 1,
    "flags": []
  },
  {
    "function": "create_configruation_from_registration",
    "file": "intent_brokering/src/intent_brokering_grpc.rs",
    "start_line": 52,
    "cyclomatic_complexity": 1,
    "nesting_depth": 1,
    "loc": 6,
    "param_count": 1,
    "flags": []
  },
  {
    "function": "map_intent_value",
    "file": "intent_brokering/src/intent_brokering_grpc.rs",
    "start_line": 59,
    "cyclomatic_complexity": 9,
    "nesting_depth": 2,
    "loc": 11,
    "param_count": 1,
    "flags": []
  },
  {
    "function": "map_intent_variant",
    "file": "intent_brokering/src/intent_brokering_grpc.rs",
    "start_line": 71,
    "cyclomatic_complexity": 8,
    "nesting_depth": 2,
    "loc": 10,
    "param_count": 1,
    "flags": []
  },
  {
    "function": "announce",
    "file": "intent_brokering/src/intent_brokering_grpc.rs",
    "start_line": 85,
    "cyclomatic_complexity": 3,
    "nesting_depth": 3,
    "loc": 19,
    "param_count": 2,
    "flags": []
  },
  {
    "function": "register",
    "file": "intent_brokering/src/intent_brokering_grpc.rs",
    "start_line": 105,
    "cyclomatic_complexity": 1,
    "nesting_depth": 1,
    "loc": 20,
    "param_count": 2,
    "flags": []
  },
  {
    "function": "fulfill",
    "file": "intent_brokering/src/intent_brokering_grpc.rs",
    "start_line": 126,
    "cyclomatic_complexity": 4,
    "nesting_depth": 2,
    "loc": 30,
    "param_count": 2,
    "flags": []
  },
  {
    "function": "resolve_service_configuration",
    "file": "intent_brokering/src/intent_brokering_grpc.rs",
    "start_line": 158,
    "cyclomatic_complexity": 1,
    "nesting_depth": 2,
    "loc": 17,
    "param_count": 1,
    "flags": []
  },
  {
    "function": "map_locality_value",
    "file": "intent_brokering/src/intent_brokering_grpc.rs",
    "start_line": 176,
    "cyclomatic_complexity": 5,
    "nesting_depth": 2,
    "loc": 7,
    "param_count": 1,
    "flags": []
  },
  {
    "function": "test_service_announcement",
    "file": "intent_brokering/src/intent_brokering_grpc.rs",
    "start_line": 203,
    "cyclomatic_complexity": 1,
    "nesting_depth": 1,
    "loc": 7,
    "param_count": 0,
    "flags": []
  },
  {
    "function": "test_register_service_with_intents",
    "file": "intent_brokering/src/intent_brokering_grpc.rs",
    "start_line": 212,
    "cyclomatic_complexity": 1,
    "nesting_depth": 1,
    "loc": 9,
    "param_count": 0,
    "flags": []
  },
  {
    "function": "test_register_service_twice_doesnt_throw_error",
    "file": "intent_brokering/src/intent_brokering_grpc.rs",
    "start_line": 223,
    "cyclomatic_complexity": 1,
    "nesting_depth": 1,
    "loc": 6,
    "param_count": 0,
    "flags": []
  },
  {
    "function": "test_register_service_twice_with_different_intents",
    "file": "intent_brokering/src/intent_brokering_grpc.rs",
    "start_line": 231,
    "cyclomatic_complexity": 1,
    "nesting_depth": 1,
    "loc": 12,
    "param_count": 0,
    "flags": []
  },
  {
    "function": "when_registering_unknown_intent_should_return_invalid_argument_error",
    "file": "intent_brokering/src/intent_brokering_grpc.rs",
    "start_line": 245,
    "cyclomatic_complexity": 1,
    "nesting_depth": 1,
    "loc": 14,
    "param_count": 0,
    "flags": []
  },
  {
    "function": "intent_match_failure_are_caught",
    "file": "intent_brokering/src/intent_brokering_grpc.rs",
    "start_line": 261,
    "cyclomatic_complexity": 1,
    "nesting_depth": 1,
    "loc": 3,
    "param_count": 0,
    "flags": []
  },
  {
    "function": "test_intent_mappings",
    "file": "intent_brokering/src/intent_brokering_grpc.rs",
    "start_line": 266,
    "cyclomatic_complexity": 8,
    "nesting_depth": 3,
    "loc": 29,
    "param_count": 0,
    "flags": []
  },
  {
    "function": "test",
    "file": "intent_brokering/src/intent_brokering_grpc.rs",
    "start_line": 281,
    "cyclomatic_complexity": 1,
    "nesting_depth": 1,
    "loc": 6,
    "param_count": 2,
    "flags": []
  },
  {
    "function": "test_intent_proto_mappings",
    "file": "intent_brokering/src/intent_brokering_grpc.rs",
    "start_line": 297,
    "cyclomatic_complexity": 8,
    "nesting_depth": 3,
    "loc": 23,
    "param_count": 0,
    "flags": []
  },
  {
    "function": "test_map_locality_value",
    "file": "intent_brokering/src/intent_brokering_grpc.rs",
    "start_line": 322,
    "cyclomatic_complexity": 1,
    "nesting_depth": 1,
    "loc": 11,
    "param_count": 0,
    "flags": []
  },
  {
    "function": "fulfill_ensures_binding_is_executed",
    "file": "intent_brokering/src/intent_brokering_grpc.rs",
    "start_line": 335,
    "cyclomatic_complexity": 1,
    "nesting_depth": 1,
    "loc": 18,
    "param_count": 0,
    "flags": []
  },
  {
    "function": "fulfill_returns_error_if_intent_not_set",
    "file": "intent_brokering/src/intent_brokering_grpc.rs",
    "start_line": 355,
    "cyclomatic_complexity": 1,
    "nesting_depth": 1,
    "loc": 12,
    "param_count": 0,
    "flags": []
  },
  {
    "function": "test_map_intent_variant",
    "file": "intent_brokering/src/intent_brokering_grpc.rs",
    "start_line": 369,
    "cyclomatic_complexity": 8,
    "nesting_depth": 3,
    "loc": 39,
    "param_count": 0,
    "flags": []
  },
  {
    "function": "resolve",
    "file": "intent_brokering/src/intent_brokering_grpc.rs",
    "start_line": 414,
    "cyclomatic_complexity": 1,
    "nesting_depth": 1,
    "loc": 6,
    "param_count": 2,
    "flags": []
  },
  {
    "function": "on_change",
    "file": "intent_brokering/src/intent_brokering_grpc.rs",
    "start_line": 423,
    "cyclomatic_complexity": 1,
    "nesting_depth": 1,
    "loc": 3,
    "param_count": 2,
    "flags": []
  },
  {
    "function": "create_fulfill",
    "file": "intent_brokering/src/intent_brokering_grpc.rs",
    "start_line": 428,
    "cyclomatic_complexity": 1,
    "nesting_depth": 1,
    "loc": 8,
    "param_count": 0,
    "flags": []
  },
  {
    "function": "setup",
    "file": "intent_brokering/src/intent_brokering_grpc.rs",
    "start_line": 437,
    "cyclomatic_complexity": 1,
    "nesting_depth": 1,
    "loc": 5,
    "param_count": 0,
    "flags": []
  },
  {
    "function": "create_announce_request",
    "file": "intent_brokering/src/intent_brokering_grpc.rs",
    "start_line": 443,
    "cyclomatic_complexity": 1,
    "nesting_depth": 1,
    "loc": 10,
    "param_count": 0,
    "flags": []
  },
  {
    "function": "create_register_request",
    "file": "intent_brokering/src/intent_brokering_grpc.rs",
    "start_line": 454,
    "cyclomatic_complexity": 1,
    "nesting_depth": 1,
    "loc": 20,
    "param_count": 0,
    "flags": []
  },
  {
    "function": "create_register_request_with_different_namespace",
    "file": "intent_brokering/src/intent_brokering_grpc.rs",
    "start_line": 475,
    "cyclomatic_complexity": 1,
    "nesting_depth": 1,
    "loc": 24,
    "param_count": 0,
    "flags": []
  },
  {
    "function": "new",
    "file": "intent_brokering/src/connection_provider.rs",
    "start_line": 57,
    "cyclomatic_complexity": 1,
    "nesting_depth": 1,
    "loc": 3,
    "param_count": 1,
    "flags": []
  },
  {
    "function": "connect",
    "file": "intent_brokering/src/connection_provider.rs",
    "start_line": 61,
    "cyclomatic_complexity": 1,
    "nesting_depth": 1,
    "loc": 5,
    "param_count": 1,
    "flags": []
  },
  {
    "function": "fulfill",
    "file": "intent_brokering/src/connection_provider.rs",
    "start_line": 70,
    "cyclomatic_complexity": 1,
    "nesting_depth": 1,
    "loc": 6,
    "param_count": 2,
    "flags": []
  },
  {
    "function": "new",
    "file": "intent_brokering/src/connection_provider.rs",
    "start_line": 97,
    "cyclomatic_complexity": 1,
    "nesting_depth": 1,
    "loc": 3,
    "param_count": 1,
    "flags": []
  },
  {
    "function": "connect",
    "file": "intent_brokering/src/connection_provider.rs",
    "start_line": 103,
    "cyclomatic_complexity": 3,
    "nesting_depth": 3,
    "loc": 17,
    "param_count": 1,
    "flags": []
  },
  {
    "function": "reusable_provider_when_already_connected_reuses_provider",
    "file": "intent_brokering/src/connection_provider.rs",
    "start_line": 137,
    "cyclomatic_complexity": 1,
    "nesting_depth": 2,
    "loc": 50,
    "param_count": 0,
    "flags": []
  },
  {
    "function": "new",
    "file": "intent_brokering/src/connection_provider.rs",
    "start_line": 145,
    "cyclomatic_complexity": 1,
    "nesting_depth": 1,
    "loc": 3,
    "param_count": 1,
    "flags": []
  },
  {
    "function": "connect",
    "file": "intent_brokering/src/connection_provider.rs",
    "start_line": 149,
    "cyclomatic_complexity": 1,
    "nesting_depth": 1,
    "loc": 3,
    "param_count": 1,
    "flags": []
  },
  {
    "function": "fulfill",
    "file": "intent_brokering/src/connection_provider.rs",
    "start_line": 161,
    "cyclomatic_complexity": 1,
    "nesting_depth": 1,
    "loc": 4,
    "param_count": 2,
    "flags": []
  },
  {
    "function": "fulfill_any",
    "file": "intent_brokering/src/connection_provider.rs",
    "start_line": 177,
    "cyclomatic_complexity": 1,
    "nesting_depth": 1,
    "loc": 3,
    "param_count": 1,
    "flags": []
  },
  {
    "function": "on_change",
    "file": "intent_brokering/src/registry.rs",
    "start_line": 31,
    "cyclomatic_complexity": 5,
    "nesting_depth": 2,
    "loc": 13,
    "param_count": 2,
    "flags": []
  },
  {
    "function": "new",
    "file": "intent_brokering/src/registry.rs",
    "start_line": 52,
    "cyclomatic_complexity": 1,
    "nesting_depth": 1,
    "loc": 3,
    "param_count": 2,
    "flags": []
  },
  {
    "function": "on_change",
    "file": "intent_brokering/src/registry.rs",
    "start_line": 58,
    "cyclomatic_complexity": 1,
    "nesting_depth": 1,
    "loc": 4,
    "param_count": 2,
    "flags": []
  },
  {
    "function": "entry_ttl",
    "file": "intent_brokering/src/registry.rs",
    "start_line": 72,
    "cyclomatic_complexity": 1,
    "nesting_depth": 1,
    "loc": 3,
    "param_count": 1,
    "flags": []
  },
  {
    "function": "set_entry_ttl_bounded",
    "file": "intent_brokering/src/registry.rs",
    "start_line": 76,
    "cyclomatic_complexity": 1,
    "nesting_depth": 1,
    "loc": 3,
    "param_count": 2,
    "flags": []
  },
  {
    "function": "default",
    "file": "intent_brokering/src/registry.rs",
    "start_line": 82,
    "cyclomatic_complexity": 1,
    "nesting_depth": 1,
    "loc": 3,
    "param_count": 0,
    "flags": []
  },
  {
    "function": "new",
    "file": "intent_brokering/src/registry.rs",
    "start_line": 102,
    "cyclomatic_complexity": 1,
    "nesting_depth": 1,
    "loc": 8,
    "param_count": 2,
    "flags": []
  },
  {
    "function": "has_service",
    "file": "intent_brokering/src/registry.rs",
    "start_line": 115,
    "cyclomatic_complexity": 1,
    "nesting_depth": 1,
    "loc": 3,
    "param_count": 2,
    "flags": []
  },
  {
    "function": "touch",
    "file": "intent_brokering/src/registry.rs",
    "start_line": 119,
    "cyclomatic_complexity": 3,
    "nesting_depth": 3,
    "loc": 8,
    "param_count": 3,
    "flags": []
  },
  {
    "function": "prune_by",
    "file": "intent_brokering/src/registry.rs",
    "start_line": 128,
    "cyclomatic_complexity": 8,
    "nesting_depth": 5,
    "loc": 33,
    "param_count": 2,
    "flags": [
      "high_nesting"
    ]
  },
  {
    "function": "<anonymous>",
    "file": "intent_brokering/src/registry.rs",
    "start_line": 130,
    "cyclomatic_complexity": 1,
    "nesting_depth": 0,
    "loc": 1,
    "param_count": 2,
    "flags": []
  },
  {
    "function": "prune",
    "file": "intent_brokering/src/registry.rs",
    "start_line": 162,
    "cyclomatic_complexity": 4,
    "nesting_depth": 1,
    "loc": 13,
    "param_count": 2,
    "flags": []
  },
  {
    "function": "upsert",
    "file": "intent_brokering/src/registry.rs",
    "start_line": 176,
    "cyclomatic_complexity": 11,
    "nesting_depth": 3,
    "loc": 54,
    "param_count": 4,
    "flags": [
      "high_complexity"
    ]
  },
  {
    "function": "starts_with_ignore_ascii_case",
    "file": "intent_brokering/src/registry.rs",
    "start_line": 182,
    "cyclomatic_complexity": 4,
    "nesting_depth": 1,
    "loc": 4,
    "param_count": 2,
    "flags": []
  },
  {
    "function": "count_external_intents",
    "file": "intent_brokering/src/registry.rs",
    "start_line": 232,
    "cyclomatic_complexity": 1,
    "nesting_depth": 1,
    "loc": 3,
    "param_count": 1,
    "flags": []
  },
  {
    "function": "new",
    "file": "intent_brokering/src/registry.rs",
    "start_line": 251,
    "cyclomatic_complexity": 1,
    "nesting_depth": 1,
    "loc": 3,
    "param_count": 0,
    "flags": []
  },
  {
    "function": "change",
    "file": "intent_brokering/src/registry.rs",
    "start_line": 255,
    "cyclomatic_complexity": 7,
    "nesting_depth": 3,
    "loc": 17,
    "param_count": 3,
    "flags": []
  },
  {
    "function": "observe",
    "file": "intent_brokering/src/registry.rs",
    "start_line": 273,
    "cyclomatic_complexity": 7,
    "nesting_depth": 3,
    "loc": 13,
    "param_count": 3,
    "flags": []
  },
  {
    "function": "new",
    "file": "intent_brokering/src/registry.rs",
    "start_line": 292,
    "cyclomatic_complexity": 1,
    "nesting_depth": 1,
    "loc": 3,
    "param_count": 2,
    "flags": []
  },
  {
    "function": "name",
    "file": "intent_brokering/src/registry.rs",
    "start_line": 296,
    "cyclomatic_complexity": 1,
    "nesting_depth": 1,
    "loc": 3,
    "param_count": 1,
    "flags": []
  },
  {
    "function": "version",
    "file": "intent_brokering/src/registry.rs",
    "start_line": 300,
    "cyclomatic_complexity": 1,
    "nesting_depth": 1,
    "loc": 3,
    "param_count": 1,
    "flags": []
  },
  {
    "function": "new",
    "file": "intent_brokering/src/registry.rs",
    "start_line": 313,
    "cyclomatic_complexity": 1,
    "nesting_depth": 1,
    "loc": 3,
    "param_count": 3,
    "flags": []
  },
  {
    "function": "locality",
    "file": "intent_brokering/src/registry.rs",
    "start_line": 317,
    "cyclomatic_complexity": 1,
    "nesting_depth": 1,
    "loc": 3,
    "param_count": 1,
    "flags": []
  },
  {
    "function": "url",
    "file": "intent_brokering/src/registry.rs",
    "start_line": 321,
    "cyclomatic_complexity": 1,
    "nesting_depth": 1,
    "loc": 3,
    "param_count": 1,
    "flags": []
  },
  {
    "function": "id",
    "file": "intent_brokering/src/registry.rs",
    "start_line": 325,
    "cyclomatic_complexity": 1,
    "nesting_depth": 1,
    "loc": 3,
    "param_count": 1,
    "flags": []
  },
  {
    "function": "new",
    "file": "intent_brokering/src/registry.rs",
    "start_line": 343,
    "cyclomatic_complexity": 1,
    "nesting_depth": 1,
    "loc": 3,
    "param_count": 2,
    "flags": []
  },
  {
    "function": "into_namespaced_intent",
    "file": "intent_brokering/src/registry.rs",
    "start_line": 347,
    "cyclomatic_complexity": 1,
    "nesting_depth": 1,
    "loc": 3,
    "param_count": 1,
    "flags": []
  },
  {
    "function": "namespace",
    "file": "intent_brokering/src/registry.rs",
    "start_line": 351,
    "cyclomatic_complexity": 1,
    "nesting_depth": 1,
    "loc": 3,
    "param_count": 1,
    "flags": []
  },
  {
    "function": "fmt",
    "file": "intent_brokering/src/registry.rs",
    "start_line": 367,
    "cyclomatic_complexity": 8,
    "nesting_depth": 2,
    "loc": 10,
    "param_count": 2,
    "flags": []
  },
  {
    "function": "now",
    "file": "intent_brokering/src/registry.rs",
    "start_line": 401,
    "cyclomatic_complexity": 1,
    "nesting_depth": 1,
    "loc": 3,
    "param_count": 0,
    "flags": []
  },
  {
    "function": "default_config",
    "file": "intent_brokering/src/registry.rs",
    "start_line": 406,
    "cyclomatic_complexity": 1,
    "nesting_depth": 1,
    "loc": 5,
    "param_count": 0,
    "flags": []
  },
  {
    "function": "config_set_entry_ttl_sets_new_value",
    "file": "intent_brokering/src/registry.rs",
    "start_line": 413,
    "cyclomatic_complexity": 2,
    "nesting_depth": 1,
    "loc": 8,
    "param_count": 0,
    "flags": []
  },
  {
    "function": "config_set_entry_ttl_sets_min_allowed_if_new_value_is_too_small",
    "file": "intent_brokering/src/registry.rs",
    "start_line": 423,
    "cyclomatic_complexity": 2,
    "nesting_depth": 1,
    "loc": 8,
    "param_count": 0,
    "flags": []
  },
  {
    "function": "when_upserting_contains_service",
    "file": "intent_brokering/src/registry.rs",
    "start_line": 433,
    "cyclomatic_complexity": 1,
    "nesting_depth": 1,
    "loc": 12,
    "param_count": 0,
    "flags": []
  },
  {
    "function": "when_upserting_empty_caches_service",
    "file": "intent_brokering/src/registry.rs",
    "start_line": 447,
    "cyclomatic_complexity": 1,
    "nesting_depth": 1,
    "loc": 12,
    "param_count": 0,
    "flags": []
  },
  {
    "function": "when_upserting_refreshes_broker_with_updated_service_configurations",
    "file": "intent_brokering/src/registry.rs",
    "start_line": 461,
    "cyclomatic_complexity": 1,
    "nesting_depth": 2,
    "loc": 16,
    "param_count": 0,
    "flags": []
  },
  {
    "function": "when_upserting_with_different_url_prunes_old_instance_and_refreshes_broker",
    "file": "intent_brokering/src/registry.rs",
    "start_line": 479,
    "cyclomatic_complexity": 1,
    "nesting_depth": 2,
    "loc": 21,
    "param_count": 0,
    "flags": []
  },
  {
    "function": "when_upserting_with_different_versions_should_be_treated_as_different_services",
    "file": "intent_brokering/src/registry.rs",
    "start_line": 502,
    "cyclomatic_complexity": 1,
    "nesting_depth": 2,
    "loc": 18,
    "param_count": 0,
    "flags": []
  },
  {
    "function": "when_service_reregisters_refreshes_all_affected_registrations_in_broker",
    "file": "intent_brokering/src/registry.rs",
    "start_line": 522,
    "cyclomatic_complexity": 1,
    "nesting_depth": 2,
    "loc": 39,
    "param_count": 0,
    "flags": []
  },
  {
    "function": "when_upserting_same_service_with_new_intents_prunes_old_intent",
    "file": "intent_brokering/src/registry.rs",
    "start_line": 563,
    "cyclomatic_complexity": 1,
    "nesting_depth": 1,
    "loc": 13,
    "param_count": 0,
    "flags": []
  },
  {
    "function": "when_upserting_same_intent_twice_is_idempotent",
    "file": "intent_brokering/src/registry.rs",
    "start_line": 578,
    "cyclomatic_complexity": 1,
    "nesting_depth": 2,
    "loc": 16,
    "param_count": 0,
    "flags": []
  },
  {
    "function": "when_upserting_system_binding_returns_error",
    "file": "intent_brokering/src/registry.rs",
    "start_line": 596,
    "cyclomatic_complexity": 1,
    "nesting_depth": 2,
    "loc": 23,
    "param_count": 0,
    "flags": []
  },
  {
    "function": "test",
    "file": "intent_brokering/src/registry.rs",
    "start_line": 605,
    "cyclomatic_complexity": 1,
    "nesting_depth": 1,
    "loc": 13,
    "param_count": 1,
    "flags": []
  },
  {
    "function": "prune_schedule",
    "file": "intent_brokering/src/registry.rs",
    "start_line": 625,
    "cyclomatic_complexity": 3,
    "nesting_depth": 2,
    "loc": 25,
    "param_count": 4,
    "flags": []
  },
  {
    "function": "prune_removes_expired_services",
    "file": "intent_brokering/src/registry.rs",
    "start_line": 657,
    "cyclomatic_complexity": 8,
    "nesting_depth": 3,
    "loc": 60,
    "param_count": 5,
    "flags": []
  },
  {
    "function": "touch_returns_false_if_service_is_unregistered",
    "file": "intent_brokering/src/registry.rs",
    "start_line": 719,
    "cyclomatic_complexity": 1,
    "nesting_depth": 1,
    "loc": 11,
    "param_count": 0,
    "flags": []
  },
  {
    "function": "touch_updates_timestamp",
    "file": "intent_brokering/src/registry.rs",
    "start_line": 732,
    "cyclomatic_complexity": 1,
    "nesting_depth": 1,
    "loc": 21,
    "param_count": 0,
    "flags": []
  },
  {
    "function": "test_create_new_service_configuration",
    "file": "intent_brokering/src/registry.rs",
    "start_line": 755,
    "cyclomatic_complexity": 1,
    "nesting_depth": 1,
    "loc": 11,
    "param_count": 0,
    "flags": []
  },
  {
    "function": "test_create_new_intent_configuration",
    "file": "intent_brokering/src/registry.rs",
    "start_line": 768,
    "cyclomatic_complexity": 1,
    "nesting_depth": 1,
    "loc": 5,
    "param_count": 0,
    "flags": []
  },
  {
    "function": "service_id_returns_name_and_version",
    "file": "intent_brokering/src/registry.rs",
    "start_line": 775,
    "cyclomatic_complexity": 1,
    "nesting_depth": 1,
    "loc": 10,
    "param_count": 0,
    "flags": []
  },
  {
    "function": "intent_kind_display_succeeds",
    "file": "intent_brokering/src/registry.rs",
    "start_line": 787,
    "cyclomatic_complexity": 8,
    "nesting_depth": 3,
    "loc": 25,
    "param_count": 0,
    "flags": []
  },
  {
    "function": "test",
    "file": "intent_brokering/src/registry.rs",
    "start_line": 808,
    "cyclomatic_complexity": 1,
    "nesting_depth": 1,
    "loc": 3,
    "param_count": 2,
    "flags": []
  },
  {
    "function": "composite_observes_both_inner_observers",
    "file": "intent_brokering/src/registry.rs",
    "start_line": 814,
    "cyclomatic_complexity": 1,
    "nesting_depth": 2,
    "loc": 24,
    "param_count": 0,
    "flags": []
  },
  {
    "function": "on_change",
    "file": "intent_brokering/src/registry.rs",
    "start_line": 821,
    "cyclomatic_complexity": 1,
    "nesting_depth": 1,
    "loc": 3,
    "param_count": 2,
    "flags": []
  },
  {
    "function": "on_change_notifies_when_namespace_change_detected",
    "file": "intent_brokering/src/registry.rs",
    "start_line": 840,
    "cyclomatic_complexity": 1,
    "nesting_depth": 3,
    "loc": 90,
    "param_count": 0,
    "flags": []
  },
  {
    "function": "intent",
    "file": "intent_brokering/src/registry.rs",
    "start_line": 845,
    "cyclomatic_complexity": 1,
    "nesting_depth": 1,
    "loc": 3,
    "param_count": 1,
    "flags": []
  },
  {
    "function": "test",
    "file": "intent_brokering/src/registry.rs",
    "start_line": 877,
    "cyclomatic_complexity": 1,
    "nesting_depth": 2,
    "loc": 52,
    "param_count": 2,
    "flags": []
  },
  {
    "function": "namespace_event",
    "file": "intent_brokering/src/registry.rs",
    "start_line": 881,
    "cyclomatic_complexity": 1,
    "nesting_depth": 1,
    "loc": 3,
    "param_count": 1,
    "flags": []
  },
  {
    "function": "new",
    "file": "intent_brokering/src/registry.rs",
    "start_line": 942,
    "cyclomatic_complexity": 1,
    "nesting_depth": 1,
    "loc": 3,
    "param_count": 0,
    "flags": []
  },
  {
    "function": "clear",
    "file": "intent_brokering/src/registry.rs",
    "start_line": 946,
    "cyclomatic_complexity": 1,
    "nesting_depth": 1,
    "loc": 3,
    "param_count": 1,
    "flags": []
  },
  {
    "function": "assert_modified",
    "file": "intent_brokering/src/registry.rs",
    "start_line": 950,
    "cyclomatic_complexity": 4,
    "nesting_depth": 2,
    "loc": 16,
    "param_count": 3,
    "flags": []
  },
  {
    "function": "<anonymous>",
    "file": "intent_brokering/src/registry.rs",
    "start_line": 953,
    "cyclomatic_complexity": 1,
    "nesting_depth": 0,
    "loc": 1,
    "param_count": 1,
    "flags": []
  },
  {
    "function": "assert_added",
    "file": "intent_brokering/src/registry.rs",
    "start_line": 967,
    "cyclomatic_complexity": 4,
    "nesting_depth": 2,
    "loc": 14,
    "param_count": 3,
    "flags": []
  },
  {
    "function": "<anonymous>",
    "file": "intent_brokering/src/registry.rs",
    "start_line": 970,
    "cyclomatic_complexity": 1,
    "nesting_depth": 0,
    "loc": 1,
    "param_count": 1,
    "flags": []
  },
  {
    "function": "assert_removed",
    "file": "intent_brokering/src/registry.rs",
    "start_line": 982,
    "cyclomatic_complexity": 4,
    "nesting_depth": 2,
    "loc": 7,
    "param_count": 2,
    "flags": []
  },
  {
    "function": "filter_map_change",
    "file": "intent_brokering/src/registry.rs",
    "start_line": 990,
    "cyclomatic_complexity": 7,
    "nesting_depth": 4,
    "loc": 19,
    "param_count": 3,
    "flags": [
      "high_nesting"
    ]
  },
  {
    "function": "<anonymous>",
    "file": "intent_brokering/src/registry.rs",
    "start_line": 993,
    "cyclomatic_complexity": 1,
    "nesting_depth": 0,
    "loc": 1,
    "param_count": 1,
    "flags": []
  },
  {
    "function": "is_empty",
    "file": "intent_brokering/src/registry.rs",
    "start_line": 1010,
    "cyclomatic_complexity": 1,
    "nesting_depth": 1,
    "loc": 3,
    "param_count": 1,
    "flags": []
  },
  {
    "function": "assert_number_of_changes",
    "file": "intent_brokering/src/registry.rs",
    "start_line": 1014,
    "cyclomatic_complexity": 1,
    "nesting_depth": 2,
    "loc": 8,
    "param_count": 2,
    "flags": []
  },
  {
    "function": "on_change",
    "file": "intent_brokering/src/registry.rs",
    "start_line": 1025,
    "cyclomatic_complexity": 5,
    "nesting_depth": 3,
    "loc": 16,
    "param_count": 2,
    "flags": []
  },
  {
    "function": "create_registry",
    "file": "intent_brokering/src/registry.rs",
    "start_line": 1043,
    "cyclomatic_complexity": 1,
    "nesting_depth": 1,
    "loc": 3,
    "param_count": 0,
    "flags": []
  },
  {
    "function": "new",
    "file": "intent_brokering/src/registry.rs",
    "start_line": 1055,
    "cyclomatic_complexity": 1,
    "nesting_depth": 1,
    "loc": 5,
    "param_count": 0,
    "flags": []
  },
  {
    "function": "build",
    "file": "intent_brokering/src/registry.rs",
    "start_line": 1061,
    "cyclomatic_complexity": 1,
    "nesting_depth": 1,
    "loc": 6,
    "param_count": 1,
    "flags": []
  },
  {
    "function": "new",
    "file": "intent_brokering/src/registry.rs",
    "start_line": 1075,
    "cyclomatic_complexity": 1,
    "nesting_depth": 1,
    "loc": 3,
    "param_count": 0,
    "flags": []
  },
  {
    "function": "dispense",
    "file": "intent_brokering/src/registry.rs",
    "start_line": 1079,
    "cyclomatic_complexity": 1,
    "nesting_depth": 1,
    "loc": 5,
    "param_count": 1,
    "flags": []
  },
  {
    "function": "with_nonce",
    "file": "intent_brokering/src/registry.rs",
    "start_line": 1085,
    "cyclomatic_complexity": 1,
    "nesting_depth": 1,
    "loc": 7,
    "param_count": 1,
    "flags": []
  },
  {
    "function": "build",
    "file": "intent_brokering/src/registry.rs",
    "start_line": 1093,
    "cyclomatic_complexity": 1,
    "nesting_depth": 1,
    "loc": 3,
    "param_count": 1,
    "flags": []
  },
  {
    "function": "version",
    "file": "intent_brokering/src/registry.rs",
    "start_line": 1097,
    "cyclomatic_complexity": 1,
    "nesting_depth": 1,
    "loc": 4,
    "param_count": 2,
    "flags": []
  },
  {
    "function": "name",
    "file": "intent_brokering/src/registry.rs",
    "start_line": 1102,
    "cyclomatic_complexity": 1,
    "nesting_depth": 1,
    "loc": 4,
    "param_count": 2,
    "flags": []
  },
  {
    "function": "url",
    "file": "intent_brokering/src/registry.rs",
    "start_line": 1107,
    "cyclomatic_complexity": 1,
    "nesting_depth": 1,
    "loc": 4,
    "param_count": 2,
    "flags": []
  },
  {
    "function": "execution_locality",
    "file": "intent_brokering/src/registry.rs",
    "start_line": 1112,
    "cyclomatic_complexity": 1,
    "nesting_depth": 1,
    "loc": 4,
    "param_count": 2,
    "flags": []
  },
  {
    "function": "new",
    "file": "intent_brokering/src/registry.rs",
    "start_line": 1122,
    "cyclomatic_complexity": 1,
    "nesting_depth": 1,
    "loc": 3,
    "param_count": 0,
    "flags": []
  },
  {
    "function": "dispense",
    "file": "intent_brokering/src/registry.rs",
    "start_line": 1126,
    "cyclomatic_complexity": 1,
    "nesting_depth": 1,
    "loc": 5,
    "param_count": 1,
    "flags": []
  },
  {
    "function": "with_nonce",
    "file": "intent_brokering/src/registry.rs",
    "start_line": 1132,
    "cyclomatic_complexity": 1,
    "nesting_depth": 1,
    "loc": 3,
    "param_count": 1,
    "flags": []
  },
  {
    "function": "namespace",
    "file": "intent_brokering/src/registry.rs",
    "start_line": 1136,
    "cyclomatic_complexity": 1,
    "nesting_depth": 1,
    "loc": 4,
    "param_count": 2,
    "flags": []
  },
  {
    "function": "build",
    "file": "intent_brokering/src/registry.rs",
    "start_line": 1141,
    "cyclomatic_complexity": 1,
    "nesting_depth": 1,
    "loc": 3,
    "param_count": 1,
    "flags": []
  },
  {
    "function": "main",
    "file": "intent_brokering/proto.rs/build.rs",
    "start_line": 8,
    "cyclomatic_complexity": 1,
    "nesting_depth": 1,
    "loc": 7,
    "param_count": 0,
    "flags": []
  },
  {
    "function": "compile_with_common",
    "file": "intent_brokering/proto.rs/build.rs",
    "start_line": 16,
    "cyclomatic_complexity": 1,
    "nesting_depth": 1,
    "loc": 5,
    "param_count": 1,
    "flags": []
  },
  {
    "function": "default",
    "file": "intent_brokering/ess/src/ess.rs",
    "start_line": 57,
    "cyclomatic_complexity": 1,
    "nesting_depth": 1,
    "loc": 6,
    "param_count": 0,
    "flags": []
  },
  {
    "function": "set_publish_buffer_size",
    "file": "intent_brokering/ess/src/ess.rs",
    "start_line": 68,
    "cyclomatic_complexity": 1,
    "nesting_depth": 1,
    "loc": 4,
    "param_count": 2,
    "flags": []
  },
  {
    "function": "set_client_buffer_size",
    "file": "intent_brokering/ess/src/ess.rs",
    "start_line": 74,
    "cyclomatic_complexity": 1,
    "nesting_depth": 1,
    "loc": 4,
    "param_count": 2,
    "flags": []
  },
  {
    "function": "new",
    "file": "intent_brokering/ess/src/ess.rs",
    "start_line": 104,
    "cyclomatic_complexity": 1,
    "nesting_depth": 1,
    "loc": 7,
    "param_count": 0,
    "flags": []
  },
  {
    "function": "new_with_config",
    "file": "intent_brokering/ess/src/ess.rs",
    "start_line": 113,
    "cyclomatic_complexity": 1,
    "nesting_depth": 1,
    "loc": 3,
    "param_count": 1,
    "flags": []
  },
  {
    "function": "publish",
    "file": "intent_brokering/ess/src/ess.rs",
    "start_line": 120,
    "cyclomatic_complexity": 3,
    "nesting_depth": 3,
    "loc": 13,
    "param_count": 3,
    "flags": []
  },
  {
    "function": "read_events",
    "file": "intent_brokering/ess/src/ess.rs",
    "start_line": 143,
    "cyclomatic_complexity": 3,
    "nesting_depth": 3,
    "loc": 13,
    "param_count": 2,
    "flags": []
  },
  {
    "function": "register_subscriptions",
    "file": "intent_brokering/ess/src/ess.rs",
    "start_line": 169,
    "cyclomatic_complexity": 2,
    "nesting_depth": 4,
    "loc": 47,
    "param_count": 3,
    "flags": [
      "high_nesting"
    ]
  },
  {
    "function": "get_subscriptions",
    "file": "intent_brokering/ess/src/ess.rs",
    "start_line": 219,
    "cyclomatic_complexity": 4,
    "nesting_depth": 2,
    "loc": 11,
    "param_count": 2,
    "flags": []
  },
  {
    "function": "deregister_subscriptions",
    "file": "intent_brokering/ess/src/ess.rs",
    "start_line": 243,
    "cyclomatic_complexity": 5,
    "nesting_depth": 6,
    "loc": 27,
    "param_count": 3,
    "flags": [
      "high_nesting"
    ]
  },
  {
    "function": "client_id",
    "file": "intent_brokering/ess/src/ess.rs",
    "start_line": 280,
    "cyclomatic_complexity": 1,
    "nesting_depth": 1,
    "loc": 3,
    "param_count": 1,
    "flags": []
  },
  {
    "function": "event_id",
    "file": "intent_brokering/ess/src/ess.rs",
    "start_line": 285,
    "cyclomatic_complexity": 1,
    "nesting_depth": 1,
    "loc": 3,
    "param_count": 1,
    "flags": []
  },
  {
    "function": "fmt",
    "file": "intent_brokering/ess/src/ess.rs",
    "start_line": 295,
    "cyclomatic_complexity": 1,
    "nesting_depth": 1,
    "loc": 3,
    "param_count": 2,
    "flags": []
  },
  {
    "function": "event_id",
    "file": "intent_brokering/ess/src/ess.rs",
    "start_line": 311,
    "cyclomatic_complexity": 1,
    "nesting_depth": 1,
    "loc": 3,
    "param_count": 1,
    "flags": []
  },
  {
    "function": "serve",
    "file": "intent_brokering/ess/src/ess.rs",
    "start_line": 330,
    "cyclomatic_complexity": 1,
    "nesting_depth": 2,
    "loc": 34,
    "param_count": 2,
    "flags": []
  },
  {
    "function": "<anonymous>",
    "file": "intent_brokering/ess/src/ess.rs",
    "start_line": 332,
    "cyclomatic_complexity": 1,
    "nesting_depth": 0,
    "loc": 1,
    "param_count": 2,
    "flags": []
  },
  {
    "function": "serve_with_handlers",
    "file": "intent_brokering/ess/src/ess.rs",
    "start_line": 374,
    "cyclomatic_complexity": 3,
    "nesting_depth": 3,
    "loc": 67,
    "param_count": 8,
    "flags": []
  },
  {
    "function": "<anonymous>",
    "file": "intent_brokering/ess/src/ess.rs",
    "start_line": 376,
    "cyclomatic_complexity": 1,
    "nesting_depth": 0,
    "loc": 1,
    "param_count": 2,
    "flags": []
  },
  {
    "function": "<anonymous>",
    "file": "intent_brokering/ess/src/ess.rs",
    "start_line": 377,
    "cyclomatic_complexity": 1,
    "nesting_depth": 0,
    "loc": 1,
    "param_count": 1,
    "flags": []
  },
  {
    "function": "<anonymous>",
    "file": "intent_brokering/ess/src/ess.rs",
    "start_line": 378,
    "cyclomatic_complexity": 1,
    "nesting_depth": 0,
    "loc": 1,
    "param_count": 1,
    "flags": []
  },
  {
    "function": "<anonymous>",
    "file": "intent_brokering/ess/src/ess.rs",
    "start_line": 379,
    "cyclomatic_complexity": 1,
    "nesting_depth": 0,
    "loc": 1,
    "param_count": 1,
    "flags": []
  },
  {
    "function": "<anonymous>",
    "file": "intent_brokering/ess/src/ess.rs",
    "start_line": 380,
    "cyclomatic_complexity": 1,
    "nesting_depth": 0,
    "loc": 1,
    "param_count": 2,
    "flags": []
  },
  {
    "function": "<anonymous>",
    "file": "intent_brokering/ess/src/ess.rs",
    "start_line": 381,
    "cyclomatic_complexity": 1,
    "nesting_depth": 0,
    "loc": 1,
    "param_count": 2,
    "flags": []
  },
  {
    "function": "<anonymous>",
    "file": "intent_brokering/ess/src/ess.rs",
    "start_line": 382,
    "cyclomatic_complexity": 1,
    "nesting_depth": 0,
    "loc": 1,
    "param_count": 2,
    "flags": []
  },
  {
    "function": "fmt",
    "file": "intent_brokering/ess/src/ess.rs",
    "start_line": 453,
    "cyclomatic_complexity": 1,
    "nesting_depth": 1,
    "loc": 3,
    "param_count": 2,
    "flags": []
  },
  {
    "function": "fmt",
    "file": "intent_brokering/ess/src/ess.rs",
    "start_line": 464,
    "cyclomatic_complexity": 3,
    "nesting_depth": 2,
    "loc": 5,
    "param_count": 2,
    "flags": []
  },
  {
    "function": "read_event",
    "file": "intent_brokering/ess/src/ess.rs",
    "start_line": 480,
    "cyclomatic_complexity": 1,
    "nesting_depth": 1,
    "loc": 3,
    "param_count": 1,
    "flags": []
  },
  {
    "function": "new",
    "file": "intent_brokering/ess/src/ess.rs",
    "start_line": 490,
    "cyclomatic_complexity": 1,
    "nesting_depth": 1,
    "loc": 3,
    "param_count": 1,
    "flags": []
  },
  {
    "function": "poll_next",
    "file": "intent_brokering/ess/src/ess.rs",
    "start_line": 498,
    "cyclomatic_complexity": 1,
    "nesting_depth": 1,
    "loc": 6,
    "param_count": 2,
    "flags": []
  },
  {
    "function": "try_send",
    "file": "intent_brokering/ess/src/ess.rs",
    "start_line": 514,
    "cyclomatic_complexity": 1,
    "nesting_depth": 1,
    "loc": 4,
    "param_count": 2,
    "flags": []
  },
  {
    "function": "dequeue_event",
    "file": "intent_brokering/ess/src/ess.rs",
    "start_line": 521,
    "cyclomatic_complexity": 2,
    "nesting_depth": 3,
    "loc": 7,
    "param_count": 1,
    "flags": []
  },
  {
    "function": "clone",
    "file": "intent_brokering/ess/src/ess.rs",
    "start_line": 531,
    "cyclomatic_complexity": 1,
    "nesting_depth": 1,
    "loc": 3,
    "param_count": 1,
    "flags": []
  },
  {
    "function": "channel",
    "file": "intent_brokering/ess/src/ess.rs",
    "start_line": 536,
    "cyclomatic_complexity": 1,
    "nesting_depth": 1,
    "loc": 4,
    "param_count": 1,
    "flags": []
  },
  {
    "function": "read_event",
    "file": "intent_brokering/ess/src/ess.rs",
    "start_line": 547,
    "cyclomatic_complexity": 1,
    "nesting_depth": 1,
    "loc": 4,
    "param_count": 2,
    "flags": []
  },
  {
    "function": "sut",
    "file": "intent_brokering/ess/src/ess.rs",
    "start_line": 553,
    "cyclomatic_complexity": 1,
    "nesting_depth": 1,
    "loc": 3,
    "param_count": 0,
    "flags": []
  },
  {
    "function": "sut_with_runtime",
    "file": "intent_brokering/ess/src/ess.rs",
    "start_line": 557,
    "cyclomatic_complexity": 1,
    "nesting_depth": 1,
    "loc": 6,
    "param_count": 0,
    "flags": []
  },
  {
    "function": "read_events_returns_new_stream_on_each_call_for_same_client",
    "file": "intent_brokering/ess/src/ess.rs",
    "start_line": 565,
    "cyclomatic_complexity": 1,
    "nesting_depth": 1,
    "loc": 12,
    "param_count": 0,
    "flags": []
  },
  {
    "function": "read_events_streams_event_on_update",
    "file": "intent_brokering/ess/src/ess.rs",
    "start_line": 579,
    "cyclomatic_complexity": 1,
    "nesting_depth": 2,
    "loc": 38,
    "param_count": 0,
    "flags": []
  },
  {
    "function": "read_events_does_not_stream_events_of_unregistered_subscriptions",
    "file": "intent_brokering/ess/src/ess.rs",
    "start_line": 619,
    "cyclomatic_complexity": 1,
    "nesting_depth": 1,
    "loc": 12,
    "param_count": 0,
    "flags": []
  },
  {
    "function": "deregistered_subscriptions_terminates_subscription_server",
    "file": "intent_brokering/ess/src/ess.rs",
    "start_line": 633,
    "cyclomatic_complexity": 1,
    "nesting_depth": 1,
    "loc": 24,
    "param_count": 0,
    "flags": []
  },
  {
    "function": "register_subscriptions_cannot_be_called_if_events_are_not_being_read",
    "file": "intent_brokering/ess/src/ess.rs",
    "start_line": 659,
    "cyclomatic_complexity": 4,
    "nesting_depth": 3,
    "loc": 11,
    "param_count": 0,
    "flags": []
  },
  {
    "function": "deregister_subscriptions_cannot_be_called_if_events_are_not_being_read",
    "file": "intent_brokering/ess/src/ess.rs",
    "start_line": 672,
    "cyclomatic_complexity": 1,
    "nesting_depth": 1,
    "loc": 9,
    "param_count": 0,
    "flags": []
  },
  {
    "function": "get_subscriptions_returns_empty_list_when_no_subscriptions_registered",
    "file": "intent_brokering/ess/src/ess.rs",
    "start_line": 683,
    "cyclomatic_complexity": 1,
    "nesting_depth": 1,
    "loc": 8,
    "param_count": 0,
    "flags": []
  },
  {
    "function": "fmt",
    "file": "intent_brokering/ess/benches/load_bench.rs",
    "start_line": 18,
    "cyclomatic_complexity": 1,
    "nesting_depth": 1,
    "loc": 3,
    "param_count": 2,
    "flags": []
  },
  {
    "function": "fmt",
    "file": "intent_brokering/ess/benches/load_bench.rs",
    "start_line": 27,
    "cyclomatic_complexity": 1,
    "nesting_depth": 1,
    "loc": 3,
    "param_count": 2,
    "flags": []
  },
  {
    "function": "event_sub_system_bench",
    "file": "intent_brokering/ess/benches/load_bench.rs",
    "start_line": 38,
    "cyclomatic_complexity": 3,
    "nesting_depth": 9,
    "loc": 49,
    "param_count": 1,
    "flags": [
      "high_nesting"
    ]
  },
  {
    "function": "bench_function",
    "file": "intent_brokering/ess/benches/load_bench.rs",
    "start_line": 88,
    "cyclomatic_complexity": 1,
    "nesting_depth": 2,
    "loc": 8,
    "param_count": 3,
    "flags": []
  },
  {
    "function": "fmt",
    "file": "intent_brokering/ess/benches/load_bench.rs",
    "start_line": 104,
    "cyclomatic_complexity": 1,
    "nesting_depth": 1,
    "loc": 3,
    "param_count": 2,
    "flags": []
  },
  {
    "function": "main",
    "file": "intent_brokering/examples/common/build.rs",
    "start_line": 8,
    "cyclomatic_complexity": 1,
    "nesting_depth": 1,
    "loc": 8,
    "param_count": 0,
    "flags": []
  },
  {
    "function": "fmt",
    "file": "intent_brokering/examples/common/src/url.rs",
    "start_line": 21,
    "cyclomatic_complexity": 5,
    "nesting_depth": 2,
    "loc": 8,
    "param_count": 2,
    "flags": []
  },
  {
    "function": "parse_socket_address",
    "file": "intent_brokering/examples/common/src/url.rs",
    "start_line": 38,
    "cyclomatic_complexity": 10,
    "nesting_depth": 3,
    "loc": 18,
    "param_count": 1,
    "flags": []
  },
  {
    "function": "register",
    "file": "intent_brokering/examples/common/src/intent_brokering/provider.rs",
    "start_line": 48,
    "cyclomatic_complexity": 1,
    "nesting_depth": 1,
    "loc": 34,
    "param_count": 7,
    "flags": []
  },
  {
    "function": "trace_result",
    "file": "intent_brokering/examples/common/src/intent_brokering/provider.rs",
    "start_line": 88,
    "cyclomatic_complexity": 3,
    "nesting_depth": 4,
    "loc": 12,
    "param_count": 2,
    "flags": [
      "high_nesting"
    ]
  },
  {
    "function": "trace_error",
    "file": "intent_brokering/examples/common/src/intent_brokering/provider.rs",
    "start_line": 93,
    "cyclomatic_complexity": 2,
    "nesting_depth": 3,
    "loc": 6,
    "param_count": 2,
    "flags": []
  },
  {
    "function": "new",
    "file": "intent_brokering/examples/common/src/intent_brokering/inspection.rs",
    "start_line": 17,
    "cyclomatic_complexity": 1,
    "nesting_depth": 1,
    "loc": 6,
    "param_count": 2,
    "flags": []
  },
  {
    "function": "get",
    "file": "intent_brokering/examples/common/src/intent_brokering/inspection.rs",
    "start_line": 24,
    "cyclomatic_complexity": 1,
    "nesting_depth": 1,
    "loc": 3,
    "param_count": 2,
    "flags": []
  },
  {
    "function": "path",
    "file": "intent_brokering/examples/common/src/intent_brokering/inspection.rs",
    "start_line": 28,
    "cyclomatic_complexity": 1,
    "nesting_depth": 1,
    "loc": 3,
    "param_count": 1,
    "flags": []
  },
  {
    "function": "fulfill",
    "file": "intent_brokering/examples/common/src/intent_brokering/inspection.rs",
    "start_line": 33,
    "cyclomatic_complexity": 1,
    "nesting_depth": 1,
    "loc": 16,
    "param_count": 2,
    "flags": []
  },
  {
    "function": "fulfillment",
    "file": "intent_brokering/examples/common/src/intent_brokering/api.rs",
    "start_line": 48,
    "cyclomatic_complexity": 1,
    "nesting_depth": 2,
    "loc": 12,
    "param_count": 1,
    "flags": []
  },
  {
    "function": "connect",
    "file": "intent_brokering/examples/common/src/intent_brokering/api.rs",
    "start_line": 90,
    "cyclomatic_complexity": 1,
    "nesting_depth": 1,
    "loc": 9,
    "param_count": 0,
    "flags": []
  },
  {
    "function": "fulfill",
    "file": "intent_brokering/examples/common/src/intent_brokering/api.rs",
    "start_line": 103,
    "cyclomatic_complexity": 1,
    "nesting_depth": 1,
    "loc": 13,
    "param_count": 3,
    "flags": []
  },
  {
    "function": "invoke",
    "file": "intent_brokering/examples/common/src/intent_brokering/api.rs",
    "start_line": 173,
    "cyclomatic_complexity": 1,
    "nesting_depth": 2,
    "loc": 21,
    "param_count": 4,
    "flags": []
  },
  {
    "function": "subscribe",
    "file": "intent_brokering/examples/common/src/intent_brokering/api.rs",
    "start_line": 195,
    "cyclomatic_complexity": 1,
    "nesting_depth": 1,
    "loc": 19,
    "param_count": 4,
    "flags": []
  },
  {
    "function": "discover",
    "file": "intent_brokering/examples/common/src/intent_brokering/api.rs",
    "start_line": 215,
    "cyclomatic_complexity": 1,
    "nesting_depth": 2,
    "loc": 13,
    "param_count": 2,
    "flags": []
  },
  {
    "function": "inspect",
    "file": "intent_brokering/examples/common/src/intent_brokering/api.rs",
    "start_line": 229,
    "cyclomatic_complexity": 4,
    "nesting_depth": 4,
    "loc": 30,
    "param_count": 3,
    "flags": [
      "high_nesting"
    ]
  },
  {
    "function": "write",
    "file": "intent_brokering/examples/common/src/intent_brokering/api.rs",
    "start_line": 260,
    "cyclomatic_complexity": 1,
    "nesting_depth": 1,
    "loc": 17,
    "param_count": 4,
    "flags": []
  },
  {
    "function": "read",
    "file": "intent_brokering/examples/common/src/intent_brokering/api.rs",
    "start_line": 278,
    "cyclomatic_complexity": 4,
    "nesting_depth": 3,
    "loc": 22,
    "param_count": 3,
    "flags": []
  },
  {
    "function": "listen",
    "file": "intent_brokering/examples/common/src/intent_brokering/api.rs",
    "start_line": 316,
    "cyclomatic_complexity": 5,
    "nesting_depth": 4,
    "loc": 60,
    "param_count": 3,
    "flags": [
      "high_nesting"
    ]
  },
  {
    "function": "from",
    "file": "intent_brokering/examples/common/src/intent_brokering/api.rs",
    "start_line": 391,
    "cyclomatic_complexity": 1,
    "nesting_depth": 1,
    "loc": 7,
    "param_count": 1,
    "flags": []
  },
  {
    "function": "new",
    "file": "intent_brokering/examples/common/src/intent_brokering/registration.rs",
    "start_line": 45,
    "cyclomatic_complexity": 1,
    "nesting_depth": 1,
    "loc": 28,
    "param_count": 6,
    "flags": []
  },
  {
    "function": "set_registration_interval",
    "file": "intent_brokering/examples/common/src/intent_brokering/registration.rs",
    "start_line": 74,
    "cyclomatic_complexity": 4,
    "nesting_depth": 3,
    "loc": 15,
    "param_count": 2,
    "flags": []
  },
  {
    "function": "set_intent_broker_url",
    "file": "intent_brokering/examples/common/src/intent_brokering/registration.rs",
    "start_line": 90,
    "cyclomatic_complexity": 5,
    "nesting_depth": 5,
    "loc": 12,
    "param_count": 2,
    "flags": [
      "high_nesting"
    ]
  },
  {
    "function": "from_env",
    "file": "intent_brokering/examples/common/src/intent_brokering/registration.rs",
    "start_line": 103,
    "cyclomatic_complexity": 1,
    "nesting_depth": 1,
    "loc": 4,
    "param_count": 1,
    "flags": []
  },
  {
    "function": "announce_url",
    "file": "intent_brokering/examples/common/src/intent_brokering/registration.rs",
    "start_line": 108,
    "cyclomatic_complexity": 1,
    "nesting_depth": 1,
    "loc": 3,
    "param_count": 1,
    "flags": []
  },
  {
    "function": "provider_url",
    "file": "intent_brokering/examples/common/src/intent_brokering/registration.rs",
    "start_line": 112,
    "cyclomatic_complexity": 1,
    "nesting_depth": 1,
    "loc": 3,
    "param_count": 1,
    "flags": []
  },
  {
    "function": "parse_provider_socket_address",
    "file": "intent_brokering/examples/common/src/intent_brokering/registration.rs",
    "start_line": 116,
    "cyclomatic_complexity": 1,
    "nesting_depth": 1,
    "loc": 5,
    "param_count": 1,
    "flags": []
  },
  {
    "function": "register",
    "file": "intent_brokering/examples/common/src/intent_brokering/registration.rs",
    "start_line": 122,
    "cyclomatic_complexity": 5,
    "nesting_depth": 5,
    "loc": 21,
    "param_count": 1,
    "flags": [
      "high_nesting"
    ]
  },
  {
    "function": "register_once",
    "file": "intent_brokering/examples/common/src/intent_brokering/registration.rs",
    "start_line": 144,
    "cyclomatic_complexity": 7,
    "nesting_depth": 5,
    "loc": 56,
    "param_count": 3,
    "flags": [
      "high_nesting"
    ]
  },
  {
    "function": "fmt",
    "file": "intent_brokering/examples/common/src/intent_brokering/value.rs",
    "start_line": 13,
    "cyclomatic_complexity": 1,
    "nesting_depth": 1,
    "loc": 3,
    "param_count": 2,
    "flags": []
  },
  {
    "function": "fmt",
    "file": "intent_brokering/examples/common/src/intent_brokering/value.rs",
    "start_line": 24,
    "cyclomatic_complexity": 1,
    "nesting_depth": 1,
    "loc": 3,
    "param_count": 2,
    "flags": []
  },
  {
    "function": "from",
    "file": "intent_brokering/examples/common/src/intent_brokering/value.rs",
    "start_line": 32,
    "cyclomatic_complexity": 1,
    "nesting_depth": 1,
    "loc": 3,
    "param_count": 1,
    "flags": []
  },
  {
    "function": "new_any",
    "file": "intent_brokering/examples/common/src/intent_brokering/value.rs",
    "start_line": 45,
    "cyclomatic_complexity": 1,
    "nesting_depth": 1,
    "loc": 3,
    "param_count": 2,
    "flags": []
  },
  {
    "function": "new_blob",
    "file": "intent_brokering/examples/common/src/intent_brokering/value.rs",
    "start_line": 49,
    "cyclomatic_complexity": 1,
    "nesting_depth": 1,
    "loc": 3,
    "param_count": 2,
    "flags": []
  },
  {
    "function": "to_i32",
    "file": "intent_brokering/examples/common/src/intent_brokering/value.rs",
    "start_line": 53,
    "cyclomatic_complexity": 3,
    "nesting_depth": 3,
    "loc": 7,
    "param_count": 1,
    "flags": []
  },
  {
    "function": "to_i64",
    "file": "intent_brokering/examples/common/src/intent_brokering/value.rs",
    "start_line": 61,
    "cyclomatic_complexity": 3,
    "nesting_depth": 3,
    "loc": 7,
    "param_count": 1,
    "flags": []
  },
  {
    "function": "to_bool",
    "file": "intent_brokering/examples/common/src/intent_brokering/value.rs",
    "start_line": 69,
    "cyclomatic_complexity": 3,
    "nesting_depth": 3,
    "loc": 7,
    "param_count": 1,
    "flags": []
  },
  {
    "function": "as_str",
    "file": "intent_brokering/examples/common/src/intent_brokering/value.rs",
    "start_line": 77,
    "cyclomatic_complexity": 3,
    "nesting_depth": 3,
    "loc": 7,
    "param_count": 1,
    "flags": []
  },
  {
    "function": "into_string",
    "file": "intent_brokering/examples/common/src/intent_brokering/value.rs",
    "start_line": 85,
    "cyclomatic_complexity": 3,
    "nesting_depth": 3,
    "loc": 7,
    "param_count": 1,
    "flags": []
  },
  {
    "function": "into_any",
    "file": "intent_brokering/examples/common/src/intent_brokering/value.rs",
    "start_line": 93,
    "cyclomatic_complexity": 3,
    "nesting_depth": 3,
    "loc": 7,
    "param_count": 1,
    "flags": []
  },
  {
    "function": "into_blob",
    "file": "intent_brokering/examples/common/src/intent_brokering/value.rs",
    "start_line": 101,
    "cyclomatic_complexity": 3,
    "nesting_depth": 3,
    "loc": 7,
    "param_count": 1,
    "flags": []
  },
  {
    "function": "try_from",
    "file": "intent_brokering/examples/common/src/intent_brokering/value.rs",
    "start_line": 113,
    "cyclomatic_complexity": 1,
    "nesting_depth": 1,
    "loc": 3,
    "param_count": 1,
    "flags": []
  },
  {
    "function": "from",
    "file": "intent_brokering/examples/common/src/intent_brokering/value.rs",
    "start_line": 119,
    "cyclomatic_complexity": 1,
    "nesting_depth": 1,
    "loc": 3,
    "param_count": 1,
    "flags": []
  },
  {
    "function": "from",
    "file": "intent_brokering/examples/common/src/intent_brokering/value.rs",
    "start_line": 125,
    "cyclomatic_complexity": 1,
    "nesting_depth": 1,
    "loc": 3,
    "param_count": 1,
    "flags": []
  },
  {
    "function": "from",
    "file": "intent_brokering/examples/common/src/intent_brokering/value.rs",
    "start_line": 131,
    "cyclomatic_complexity": 1,
    "nesting_depth": 1,
    "loc": 3,
    "param_count": 1,
    "flags": []
  },
  {
    "function": "from",
    "file": "intent_brokering/examples/common/src/intent_brokering/value.rs",
    "start_line": 137,
    "cyclomatic_complexity": 1,
    "nesting_depth": 1,
    "loc": 3,
    "param_count": 1,
    "flags": []
  },
  {
    "function": "from",
    "file": "intent_brokering/examples/common/src/intent_brokering/value.rs",
    "start_line": 143,
    "cyclomatic_complexity": 1,
    "nesting_depth": 1,
    "loc": 3,
    "param_count": 1,
    "flags": []
  },
  {
    "function": "from",
    "file": "intent_brokering/examples/common/src/intent_brokering/value.rs",
    "start_line": 149,
    "cyclomatic_complexity": 1,
    "nesting_depth": 1,
    "loc": 3,
    "param_count": 1,
    "flags": []
  },
  {
    "function": "from",
    "file": "intent_brokering/examples/common/src/intent_brokering/value.rs",
    "start_line": 155,
    "cyclomatic_complexity": 1,
    "nesting_depth": 1,
    "loc": 3,
    "param_count": 1,
    "flags": []
  },
  {
    "function": "from",
    "file": "intent_brokering/examples/common/src/intent_brokering/value.rs",
    "start_line": 161,
    "cyclomatic_complexity": 1,
    "nesting_depth": 1,
    "loc": 3,
    "param_count": 1,
    "flags": []
  },
  {
    "function": "from",
    "file": "intent_brokering/examples/common/src/intent_brokering/value.rs",
    "start_line": 167,
    "cyclomatic_complexity": 1,
    "nesting_depth": 1,
    "loc": 3,
    "param_count": 1,
    "flags": []
  },
  {
    "function": "on_set",
    "file": "intent_brokering/examples/common/src/intent_brokering/streaming.rs",
    "start_line": 21,
    "cyclomatic_complexity": 1,
    "nesting_depth": 1,
    "loc": 3,
    "param_count": 3,
    "flags": []
  },
  {
    "function": "ess",
    "file": "intent_brokering/examples/common/src/intent_brokering/streaming.rs",
    "start_line": 36,
    "cyclomatic_complexity": 1,
    "nesting_depth": 1,
    "loc": 3,
    "param_count": 1,
    "flags": []
  },
  {
    "function": "new",
    "file": "intent_brokering/examples/common/src/intent_brokering/streaming.rs",
    "start_line": 42,
    "cyclomatic_complexity": 1,
    "nesting_depth": 1,
    "loc": 5,
    "param_count": 0,
    "flags": []
  },
  {
    "function": "default",
    "file": "intent_brokering/examples/common/src/intent_brokering/streaming.rs",
    "start_line": 50,
    "cyclomatic_complexity": 1,
    "nesting_depth": 1,
    "loc": 3,
    "param_count": 0,
    "flags": []
  },
  {
    "function": "get",
    "file": "intent_brokering/examples/common/src/intent_brokering/streaming.rs",
    "start_line": 60,
    "cyclomatic_complexity": 1,
    "nesting_depth": 1,
    "loc": 3,
    "param_count": 2,
    "flags": []
  },
  {
    "function": "set",
    "file": "intent_brokering/examples/common/src/intent_brokering/streaming.rs",
    "start_line": 65,
    "cyclomatic_complexity": 1,
    "nesting_depth": 1,
    "loc": 3,
    "param_count": 3,
    "flags": []
  },
  {
    "function": "subscribe",
    "file": "intent_brokering/examples/common/src/intent_brokering/streaming.rs",
    "start_line": 79,
    "cyclomatic_complexity": 1,
    "nesting_depth": 1,
    "loc": 4,
    "param_count": 2,
    "flags": []
  },
  {
    "function": "read",
    "file": "intent_brokering/examples/common/src/intent_brokering/streaming.rs",
    "start_line": 84,
    "cyclomatic_complexity": 1,
    "nesting_depth": 1,
    "loc": 6,
    "param_count": 2,
    "flags": []
  },
  {
    "function": "from",
    "file": "intent_brokering/examples/common/src/examples/detection.rs",
    "start_line": 18,
    "cyclomatic_complexity": 1,
    "nesting_depth": 1,
    "loc": 3,
    "param_count": 1,
    "flags": []
  },
  {
    "function": "new",
    "file": "intent_brokering/examples/common/src/examples/detection.rs",
    "start_line": 26,
    "cyclomatic_complexity": 1,
    "nesting_depth": 1,
    "loc": 3,
    "param_count": 1,
    "flags": []
  },
  {
    "function": "new",
    "file": "intent_brokering/examples/common/src/examples/detection.rs",
    "start_line": 38,
    "cyclomatic_complexity": 1,
    "nesting_depth": 1,
    "loc": 3,
    "param_count": 2,
    "flags": []
  },
  {
    "function": "try_from",
    "file": "intent_brokering/examples/common/src/examples/detection.rs",
    "start_line": 46,
    "cyclomatic_complexity": 9,
    "nesting_depth": 4,
    "loc": 22,
    "param_count": 1,
    "flags": [
      "high_nesting"
    ]
  },
  {
    "function": "from",
    "file": "intent_brokering/examples/common/src/examples/detection.rs",
    "start_line": 71,
    "cyclomatic_complexity": 1,
    "nesting_depth": 1,
    "loc": 17,
    "param_count": 1,
    "flags": []
  },
  {
    "function": "wain",
    "file": "intent_brokering/examples/applications/kv-app/src/main.rs",
    "start_line": 23,
    "cyclomatic_complexity": 1,
    "nesting_depth": 1,
    "loc": 23,
    "param_count": 0,
    "flags": []
  },
  {
    "function": "new",
    "file": "intent_brokering/examples/applications/kv-app/src/intent_provider.rs",
    "start_line": 29,
    "cyclomatic_complexity": 1,
    "nesting_depth": 1,
    "loc": 3,
    "param_count": 2,
    "flags": []
  },
  {
    "function": "write",
    "file": "intent_brokering/examples/applications/kv-app/src/intent_provider.rs",
    "start_line": 33,
    "cyclomatic_complexity": 1,
    "nesting_depth": 1,
    "loc": 9,
    "param_count": 2,
    "flags": []
  },
  {
    "function": "fulfill",
    "file": "intent_brokering/examples/applications/kv-app/src/intent_provider.rs",
    "start_line": 46,
    "cyclomatic_complexity": 7,
    "nesting_depth": 2,
    "loc": 30,
    "param_count": 2,
    "flags": []
  },
  {
    "function": "connect_intent_brokering_client",
    "file": "intent_brokering/examples/applications/simple-provider/src/main.rs",
    "start_line": 39,
    "cyclomatic_complexity": 1,
    "nesting_depth": 2,
    "loc": 12,
    "param_count": 2,
    "flags": []
  },
  {
    "function": "register_and_announce_once",
    "file": "intent_brokering/examples/applications/simple-provider/src/main.rs",
    "start_line": 52,
    "cyclomatic_complexity": 4,
    "nesting_depth": 4,
    "loc": 58,
    "param_count": 2,
    "flags": [
      "high_nesting"
    ]
  },
  {
    "function": "register_and_announce_provider",
    "file": "intent_brokering/examples/applications/simple-provider/src/main.rs",
    "start_line": 111,
    "cyclomatic_complexity": 5,
    "nesting_depth": 6,
    "loc": 24,
    "param_count": 2,
    "flags": [
      "high_nesting"
    ]
  },
  {
    "function": "wain",
    "file": "intent_brokering/examples/applications/simple-provider/src/main.rs",
    "start_line": 139,
    "cyclomatic_complexity": 1,
    "nesting_depth": 1,
    "loc": 34,
    "param_count": 0,
    "flags": []
  },
  {
    "function": "new",
    "file": "intent_brokering/examples/applications/simple-provider/src/intent_provider.rs",
    "start_line": 25,
    "cyclomatic_complexity": 1,
    "nesting_depth": 1,
    "loc": 3,
    "param_count": 1,
    "flags": []
  },
  {
    "function": "fulfill",
    "file": "intent_brokering/examples/applications/simple-provider/src/intent_provider.rs",
    "start_line": 32,
    "cyclomatic_complexity": 4,
    "nesting_depth": 2,
    "loc": 27,
    "param_count": 2,
    "flags": []
  },
  {
    "function": "wain",
    "file": "intent_brokering/examples/applications/lt-provider/src/main.rs",
    "start_line": 39,
    "cyclomatic_complexity": 4,
    "nesting_depth": 2,
    "loc": 25,
    "param_count": 0,
    "flags": []
  },
  {
    "function": "new",
    "file": "intent_brokering/examples/applications/lt-provider/src/main.rs",
    "start_line": 72,
    "cyclomatic_complexity": 1,
    "nesting_depth": 1,
    "loc": 4,
    "param_count": 0,
    "flags": []
  },
  {
    "function": "normal",
    "file": "intent_brokering/examples/applications/lt-provider/src/main.rs",
    "start_line": 77,
    "cyclomatic_complexity": 1,
    "nesting_depth": 1,
    "loc": 13,
    "param_count": 2,
    "flags": []
  },
  {
    "function": "fulfill",
    "file": "intent_brokering/examples/applications/lt-provider/src/main.rs",
    "start_line": 94,
    "cyclomatic_complexity": 5,
    "nesting_depth": 5,
    "loc": 25,
    "param_count": 2,
    "flags": [
      "high_nesting"
    ]
  },
  {
    "function": "wain",
    "file": "intent_brokering/examples/applications/invoke-command/src/main.rs",
    "start_line": 22,
    "cyclomatic_complexity": 1,
    "nesting_depth": 1,
    "loc": 21,
    "param_count": 0,
    "flags": []
  },
  {
    "function": "new",
    "file": "intent_brokering/examples/applications/invoke-command/src/intent_provider.rs",
    "start_line": 25,
    "cyclomatic_complexity": 1,
    "nesting_depth": 1,
    "loc": 3,
    "param_count": 1,
    "flags": []
  },
  {
    "function": "parse_and_print_json",
    "file": "intent_brokering/examples/applications/invoke-command/src/intent_provider.rs",
    "start_line": 30,
    "cyclomatic_complexity": 1,
    "nesting_depth": 1,
    "loc": 8,
    "param_count": 1,
    "flags": []
  },
  {
    "function": "invoke",
    "file": "intent_brokering/examples/applications/invoke-command/src/intent_provider.rs",
    "start_line": 40,
    "cyclomatic_complexity": 7,
    "nesting_depth": 4,
    "loc": 21,
    "param_count": 2,
    "flags": [
      "high_nesting"
    ]
  },
  {
    "function": "fulfill",
    "file": "intent_brokering/examples/applications/invoke-command/src/intent_provider.rs",
    "start_line": 65,
    "cyclomatic_complexity": 5,
    "nesting_depth": 2,
    "loc": 28,
    "param_count": 2,
    "flags": []
  },
  {
    "function": "wain",
    "file": "intent_brokering/examples/applications/lt-consumer/src/main.rs",
    "start_line": 55,
    "cyclomatic_complexity": 18,
    "nesting_depth": 6,
    "loc": 133,
    "param_count": 0,
    "flags": [
      "high_complexity",
      "high_nesting",
      "high_loc"
    ]
  },
  {
    "function": "evaluate_docker_stats",
    "file": "intent_brokering/examples/applications/lt-consumer/src/main.rs",
    "start_line": 189,
    "cyclomatic_complexity": 11,
    "nesting_depth": 7,
    "loc": 58,
    "param_count": 2,
    "flags": [
      "high_complexity",
      "high_nesting"
    ]
  },
  {
    "function": "execute",
    "file": "intent_brokering/examples/applications/lt-consumer/src/main.rs",
    "start_line": 197,
    "cyclomatic_complexity": 10,
    "nesting_depth": 6,
    "loc": 49,
    "param_count": 2,
    "flags": [
      "high_nesting"
    ]
  },
  {
    "function": "<anonymous>",
    "file": "intent_brokering/tests/provider.rs",
    "start_line": 23,
    "cyclomatic_complexity": 1,
    "nesting_depth": 0,
    "loc": 1,
    "param_count": 1,
    "flags": []
  },
  {
    "function": "new",
    "file": "intent_brokering/tests/provider.rs",
    "start_line": 28,
    "cyclomatic_complexity": 1,
    "nesting_depth": 1,
    "loc": 3,
    "param_count": 0,
    "flags": []
  },
  {
    "function": "with_on_invoke",
    "file": "intent_brokering/tests/provider.rs",
    "start_line": 32,
    "cyclomatic_complexity": 1,
    "nesting_depth": 1,
    "loc": 3,
    "param_count": 2,
    "flags": []
  },
  {
    "function": "<anonymous>",
    "file": "intent_brokering/tests/provider.rs",
    "start_line": 32,
    "cyclomatic_complexity": 1,
    "nesting_depth": 0,
    "loc": 1,
    "param_count": 1,
    "flags": []
  },
  {
    "function": "serve",
    "file": "intent_brokering/tests/provider.rs",
    "start_line": 36,
    "cyclomatic_complexity": 1,
    "nesting_depth": 1,
    "loc": 13,
    "param_count": 2,
    "flags": []
  },
  {
    "function": "fulfill",
    "file": "intent_brokering/tests/provider.rs",
    "start_line": 53,
    "cyclomatic_complexity": 6,
    "nesting_depth": 5,
    "loc": 27,
    "param_count": 2,
    "flags": [
      "high_nesting"
    ]
  },
  {
    "function": "when_fulfill_invoke_intent_returns_response",
    "file": "intent_brokering/tests/chariott_integration.rs",
    "start_line": 40,
    "cyclomatic_complexity": 1,
    "nesting_depth": 1,
    "loc": 14,
    "param_count": 0,
    "flags": []
  },
  {
    "function": "when_two_providers_invoke_intent_prioritizes_cloud_response",
    "file": "intent_brokering/tests/chariott_integration.rs",
    "start_line": 56,
    "cyclomatic_complexity": 1,
    "nesting_depth": 1,
    "loc": 18,
    "param_count": 0,
    "flags": []
  },
  {
    "function": "when_two_providers_invoke_intent_falls_back_to_local_response",
    "file": "intent_brokering/tests/chariott_integration.rs",
    "start_line": 76,
    "cyclomatic_complexity": 1,
    "nesting_depth": 1,
    "loc": 18,
    "param_count": 0,
    "flags": []
  },
  {
    "function": "when_invoke_intent_arguments_are_passed_correctly",
    "file": "intent_brokering/tests/chariott_integration.rs",
    "start_line": 96,
    "cyclomatic_complexity": 1,
    "nesting_depth": 2,
    "loc": 24,
    "param_count": 0,
    "flags": []
  },
  {
    "function": "when_cancelled_shuts_down_provider",
    "file": "intent_brokering/tests/chariott_integration.rs",
    "start_line": 122,
    "cyclomatic_complexity": 1,
    "nesting_depth": 1,
    "loc": 20,
    "param_count": 0,
    "flags": []
  },
  {
    "function": "local",
    "file": "intent_brokering/tests/chariott_integration.rs",
    "start_line": 156,
    "cyclomatic_complexity": 1,
    "nesting_depth": 1,
    "loc": 3,
    "param_count": 1,
    "flags": []
  },
  {
    "function": "cloud",
    "file": "intent_brokering/tests/chariott_integration.rs",
    "start_line": 160,
    "cyclomatic_complexity": 1,
    "nesting_depth": 1,
    "loc": 3,
    "param_count": 1,
    "flags": []
  },
  {
    "function": "setup",
    "file": "intent_brokering/tests/chariott_integration.rs",
    "start_line": 165,
    "cyclomatic_complexity": 1,
    "nesting_depth": 1,
    "loc": 3,
    "param_count": 1,
    "flags": []
  },
  {
    "function": "setup_multiple",
    "file": "intent_brokering/tests/chariott_integration.rs",
    "start_line": 169,
    "cyclomatic_complexity": 1,
    "nesting_depth": 2,
    "loc": 19,
    "param_count": 1,
    "flags": []
  },
  {
    "function": "fulfill",
    "file": "intent_brokering/tests/chariott_integration.rs",
    "start_line": 191,
    "cyclomatic_complexity": 1,
    "nesting_depth": 1,
    "loc": 13,
    "param_count": 3,
    "flags": []
  },
  {
    "function": "get_port",
    "file": "intent_brokering/tests/chariott_integration.rs",
    "start_line": 206,
    "cyclomatic_complexity": 1,
    "nesting_depth": 1,
    "loc": 4,
    "param_count": 0,
    "flags": []
  },
  {
    "function": "expired_registrations_are_pruned_after_ttl",
    "file": "intent_brokering/tests/registry-e2e.rs",
    "start_line": 21,
    "cyclomatic_complexity": 2,
    "nesting_depth": 1,
    "loc": 30,
    "param_count": 0,
    "flags": []
  },
  {
    "function": "when_provider_registers_notifies_registry_observers",
    "file": "intent_brokering/tests/registry-e2e.rs",
    "start_line": 53,
    "cyclomatic_complexity": 1,
    "nesting_depth": 2,
    "loc": 32,
    "param_count": 0,
    "flags": []
  },
  {
    "function": "namespace_event",
    "file": "intent_brokering/tests/registry-e2e.rs",
    "start_line": 54,
    "cyclomatic_complexity": 1,
    "nesting_depth": 1,
    "loc": 3,
    "param_count": 1,
    "flags": []
  },
  {
    "function": "setup",
    "file": "intent_brokering/tests/registry-e2e.rs",
    "start_line": 86,
    "cyclomatic_complexity": 1,
    "nesting_depth": 1,
    "loc": 3,
    "param_count": 0,
    "flags": []
  },
  {
    "function": "get_uuid",
    "file": "intent_brokering/tests/common.rs",
    "start_line": 5,
    "cyclomatic_complexity": 1,
    "nesting_depth": 1,
    "loc": 3,
    "param_count": 0,
    "flags": []
  },
  {
    "function": "when_key_does_not_exist_returns_none",
    "file": "intent_brokering/tests/store-e2e.rs",
    "start_line": 21,
    "cyclomatic_complexity": 1,
    "nesting_depth": 1,
    "loc": 12,
    "param_count": 0,
    "flags": []
  },
  {
    "function": "when_writing_value_returns_value_on_read",
    "file": "intent_brokering/tests/store-e2e.rs",
    "start_line": 35,
    "cyclomatic_complexity": 1,
    "nesting_depth": 1,
    "loc": 15,
    "param_count": 0,
    "flags": []
  },
  {
    "function": "when_provider_does_not_exist_returns_error",
    "file": "intent_brokering/tests/store-e2e.rs",
    "start_line": 52,
    "cyclomatic_complexity": 1,
    "nesting_depth": 1,
    "loc": 10,
    "param_count": 0,
    "flags": []
  },
  {
    "function": "when_writing_while_streaming_publishes_value",
    "file": "intent_brokering/tests/store-e2e.rs",
    "start_line": 64,
    "cyclomatic_complexity": 1,
    "nesting_depth": 1,
    "loc": 19,
    "param_count": 0,
    "flags": []
  },
  {
    "function": "when_streaming_increases_sequence_number",
    "file": "intent_brokering/tests/store-e2e.rs",
    "start_line": 85,
    "cyclomatic_complexity": 1,
    "nesting_depth": 2,
    "loc": 28,
    "param_count": 0,
    "flags": []
  },
  {
    "function": "when_writing_to_a_different_key_does_not_publish_value",
    "file": "intent_brokering/tests/store-e2e.rs",
    "start_line": 115,
    "cyclomatic_complexity": 2,
    "nesting_depth": 1,
    "loc": 23,
    "param_count": 0,
    "flags": []
  },
  {
    "function": "setup",
    "file": "intent_brokering/tests/store-e2e.rs",
    "start_line": 139,
    "cyclomatic_complexity": 1,
    "nesting_depth": 1,
    "loc": 3,
    "param_count": 0,
    "flags": []
  },
  {
    "function": "new",
    "file": "intent_brokering/keyvalue/src/key_value_store.rs",
    "start_line": 77,
    "cyclomatic_complexity": 1,
    "nesting_depth": 1,
    "loc": 3,
    "param_count": 1,
    "flags": []
  },
  {
    "function": "get",
    "file": "intent_brokering/keyvalue/src/key_value_store.rs",
    "start_line": 88,
    "cyclomatic_complexity": 1,
    "nesting_depth": 1,
    "loc": 7,
    "param_count": 2,
    "flags": []
  },
  {
    "function": "set",
    "file": "intent_brokering/keyvalue/src/key_value_store.rs",
    "start_line": 103,
    "cyclomatic_complexity": 3,
    "nesting_depth": 3,
    "loc": 8,
    "param_count": 3,
    "flags": []
  },
  {
    "function": "on_set",
    "file": "intent_brokering/keyvalue/src/key_value_store.rs",
    "start_line": 125,
    "cyclomatic_complexity": 1,
    "nesting_depth": 1,
    "loc": 3,
    "param_count": 3,
    "flags": []
  },
  {
    "function": "setup_none_observer",
    "file": "intent_brokering/keyvalue/src/key_value_store.rs",
    "start_line": 130,
    "cyclomatic_complexity": 1,
    "nesting_depth": 1,
    "loc": 6,
    "param_count": 0,
    "flags": []
  },
  {
    "function": "test_key_value_store",
    "file": "intent_brokering/keyvalue/src/key_value_store.rs",
    "start_line": 138,
    "cyclomatic_complexity": 1,
    "nesting_depth": 1,
    "loc": 5,
    "param_count": 0,
    "flags": []
  },
  {
    "function": "test_key_value_store_with_custom_struct",
    "file": "intent_brokering/keyvalue/src/key_value_store.rs",
    "start_line": 145,
    "cyclomatic_complexity": 1,
    "nesting_depth": 1,
    "loc": 36,
    "param_count": 0,
    "flags": []
  },
  {
    "function": "test_key_value_store_with_observer",
    "file": "intent_brokering/keyvalue/src/key_value_store.rs",
    "start_line": 183,
    "cyclomatic_complexity": 1,
    "nesting_depth": 2,
    "loc": 15,
    "param_count": 0,
    "flags": []
  },
  {
    "function": "on_set",
    "file": "intent_brokering/keyvalue/src/key_value_store.rs",
    "start_line": 188,
    "cyclomatic_complexity": 1,
    "nesting_depth": 1,
    "loc": 4,
    "param_count": 3,
    "flags": []
  },
  {
    "function": "test_observer_gets_notified_twice_when_setting_an_unchanged_value",
    "file": "intent_brokering/keyvalue/src/key_value_store.rs",
    "start_line": 200,
    "cyclomatic_complexity": 1,
    "nesting_depth": 2,
    "loc": 21,
    "param_count": 0,
    "flags": []
  },
  {
    "function": "on_set",
    "file": "intent_brokering/keyvalue/src/key_value_store.rs",
    "start_line": 207,
    "cyclomatic_complexity": 1,
    "nesting_depth": 1,
    "loc": 5,
    "param_count": 3,
    "flags": []
  }
]