{
  "function": "main",
  "nodes": [
    {
      "id": 0,
      "label": "entry:main",
      "line": 160
    },
    {
      "id": 1,
      "label": "loop (for_statement)",
      "line": 177
    },
    {
      "id": 2,
      "label": "loop_exit",
      "line": 208
    },
    {
      "id": 3,
      "label": "body",
      "line": 177
    },
    {
      "id": 4,
      "label": "if (...)",
      "line": 210
    },
    {
      "id": 5,
      "label": "merge",
      "line": 223
    },
    {
      "id": 6,
      "label": "then",
      "line": 210
    },
    {
      "id": 7,
      "label": "if (...)",
      "line": 225
    },
    {
      "id": 8,
      "label": "merge",
      "line": 227
    },
    {
      "id": 9,
      "label": "then",
      "line": 225
    },
    {
      "id": 10,
      "label": "if (...)",
      "line": 232
    },
    {
      "id": 11,
      "label": "merge",
      "line": 235
    },
    {
      "id": 12,
      "label": "then",
      "line": 232
    },
    {
      "id": 13,
      "label": "if (...)",
      "line": 236
    },
    {
      "id": 14,
      "label": "merge",
      "line": 239
    },
    {
      "id": 15,
      "label": "then",
      "line": 236
    },
    {
      "id": 16,
      "label": "if (...)",
      "line": 247
    },
    {
      "id": 17,
      "label": "merge",
      "line": 250
    },
    {
      "id": 18,
      "label": "then",
      "line": 247
    },
    {
      "id": 19,
      "label": "if (...)",
      "line": 251
    },
    {
      "id": 20,
      "label": "merge",
      "line": 256
    },
    {
      "id": 21,
      "label": "then",
      "line": 251
    },
    {
      "id": 22,
      "label": "else",
      "line": 251
    },
    {
      "id": 23,
      "label": "return_statement",
      "line": 257
    },
    {
      "id": 24,
      "label": "exit:main",
      "line": 258
    }
  ],
  "edges": [
    {
      "from": 0,
      "to": 1
    },
    {
      "from": 1,
      "to": 2,
      "label": "done"
    },
    {
      "from": 1,
      "to": 3,
      "label": "continue"
    },
    {
      "from": 3,
      "to": 1,
      "label": "back"
    },
    {
      "from": 2,
      "to": 4
    },
    {
      "from": 4,
      "to": 6,
      "label": "true"
    },
    {
      "from": 6,
      "to": 5
    },
    {
      "from": 4,
      "to": 5,
      "label": "false"
    },
    {
      "from": 5,
      "to": 7
    },
    {
      "from": 7,
      "to": 9,
      "label": "true"
    },
    {
      "from": 9,
      "to": 8
    },
    {
      "from": 7,
      "to": 8,
      "label": "false"
    },
    {
      "from": 8,
      "to": 10
    },
    {
      "from": 10,
      "to": 12,
      "label": "true"
    },
    {
      "from": 12,
      "to": 11
    },
    {
      "from": 10,
      "to": 11,
      "label": "false"
    },
    {
      "from": 11,
      "to": 13
    },
    {
      "from": 13,
      "to": 15,
      "label": "true"
    },
    {
      "from": 15,
      "to": 14
    },
    {
      "from": 13,
      "to": 14,
      "label": "false"
    },
    {
      "from": 14,
      "to": 16
    },
    {
      "from": 16,
      "to": 18,
      "label": "true"
    },
    {
      "from": 18,
      "to": 17
    },
    {
      "from": 16,
      "to": 17,
      "label": "false"
    },
    {
      "from": 17,
      "to": 19
    },
    {
      "from": 19,
      "to": 21,
      "label": "true"
    },
    {
      "from": 21,
      "to": 20
    },
    {
      "from": 19,
      "to": 22,
      "label": "false"
    },
    {
      "from": 22,
      "to": 20
    },
    {
      "from": 20,
      "to": 23
    },
    {
      "from": 20,
      "to": 24
    }
  ]
}